{"has_more_entries": true, "subscriptions": "", "error": "", "posts": [{"is_locked": false, "tweet_id": "", "sticky_comment": 0, "is_video_mp4": false, "type": "link", "uuid": "1AR0eKIskC", "is_twitter": false, "is_admin": false, "score": 62, "suggested_sort": 0, "post_flair_class": "", "id": 8069328, "raw_content": "", "author": "KMOB", "created": 1759012200086, "profile_picture": "", "community": "TheDonald", "ad_tier": 2, "last_comment_author": "MagaAssRipper", "is_video": false, "video_link": "", "is_new_user": false, "domain": "media.scored.co", "is_crosspost": false, "preview": "https://media.scored.co/preview/1AR0eKIskC.png", "removal_source": "", "link": "https://media.scored.co/post/A0PWFDcZEHIz.jpeg", "author_flair_class": "", "is_removed": false, "media": {"resized_resolutions": [{"reference": "/scale/qsYTRCuYIaHWVRkh.png", "width": 519, "content-type": "png", "height": 759}], "blurhash": "UFBM*[~q0K0000Di-;?cM{Rjoft7~W%gE1D%", "full_resolution": [759, 519]}, "title": "Potential Government Shutdown Sep 30, 2025 Could be an Excellent Way To Take a \"Break\" - And Do Some House Cleaning    _ Time to Take Out the Trash", "last_comment_created": 1759015120432, "content": "", "score_down": 0, "author_flair_text": "", "pro_tier": 0, "is_stickied": false, "is_nsfw": false, "is_deleted": false, "is_image": true, "comments": 3, "score_up": 62, "is_edited": false, "is_moderator": false, "awards": 0, "vote_state": 2, "link_metadata": {"status": 200}, "post_flair_text": "", "archive_id": ""}, {"is_locked": false, "tweet_id": "", "sticky_comment": 0, "is_video_mp4": false, "type": "link", "uuid": "1AR0eKJ9j0", "is_twitter": false, "is_admin": false, "score": 55, "suggested_sort": 0, "post_flair_class": "", "id": 8069412, "raw_content": "", "author": "AR_MAGA", "created": 1759014460653, "profile_picture": "", "community": "TheDonald", "ad_tier": 2, "last_comment_author": "blockchain-the-vote", "is_video": false, "video_link": "", "is_new_user": false, "domain": "media.scored.co", "is_crosspost": false, "preview": "https://media.scored.co/preview/1AR0eKJ9j0.png", "removal_source": "", "link": "https://media.scored.co/post/5a30JPQ2QKMf.jpeg", "author_flair_class": "", "is_removed": false, "media": {"resized_resolutions": [{"reference": "/scale/LnWmJCLtynrQ4mPq.jpeg", "width": 768, "content-type": "jpeg", "height": 576}], "blurhash": "UGEMd|?d=reR_LMxtTtT9HIToxW=4.XSoHRO", "full_resolution": [3120, 4160]}, "title": "Roger Waters, along with Petro, instigating American soldiers to rebel against Trump. What's Rubio waiting for to ban him from entering the country forever? ", "last_comment_created": 1759018974025, "content": "", "score_down": 0, "author_flair_text": "", "pro_tier": 0, "is_stickied": false, "is_nsfw": false, "is_deleted": false, "is_image": true, "comments": 6, "score_up": 55, "is_edited": false, "is_moderator": false, "awards": 0, "vote_state": 2, "link_metadata": {"status": 200}, "post_flair_text": "", "archive_id": ""}, {"is_locked": false, "tweet_id": "", "sticky_comment": 0, "is_video_mp4": false, "type": "link", "uuid": "1AR0eJC8mW", "is_twitter": false, "is_admin": false, "score": 98, "suggested_sort": 0, "post_flair_class": "nsfcucks", "id": 8068960, "raw_content": "", "author": "Trick", "created": 1759003132092, "profile_picture": "", "community": "TheDonald", "ad_tier": 2, "last_comment_author": "Liberats", "is_video": false, "video_link": "", "is_new_user": false, "domain": "pjmedia.com", "is_crosspost": false, "preview": "https://media.scored.co/preview/1AR0eJC8mW.png", "removal_source": "", "link": "https://pjmedia.com/matt-margolis/2025/09/27/john-brennan-wants-trump-to-move-on-from-the-russian-collusion-hoax-n4944204", "author_flair_class": "", "is_removed": false, "media": {"resized_resolutions": [], "blurhash": "", "full_resolution": []}, "title": "FAT CHANCE: John Brennan Wants Us to Move On from the Russian Collusion Hoax", "last_comment_created": 1759014955266, "content": "", "score_down": 1, "author_flair_text": "", "pro_tier": 0, "is_stickied": false, "is_nsfw": false, "is_deleted": false, "is_image": false, "comments": 13, "score_up": 99, "is_edited": false, "is_moderator": false, "awards": 0, "vote_state": 2, "link_metadata": {"description": "John Brennan urges conservatives to move on from the Russian collusion narrative.", "large_image": "n8OYUvH0g1BbqOGI.png", "title": "FAT CHANCE: John Brennan Wants Us to Move On from the Russian Collusion Hoax"}, "post_flair_text": "\u00a0\u00a0\u00a0\u00a0\u00a0\u00a0\u00a0\u00a0\u00a0\u00a0\u00a0STUPID\u00a0\u00a0S.O.B.\u00a0\u00a0", "archive_id": ""}, {"is_locked": false, "tweet_id": "", "sticky_comment": 0, "is_video_mp4": false, "type": "link", "uuid": "1AR0eJ9waf", "is_twitter": false, "is_admin": false, "score": 345, "suggested_sort": 0, "post_flair_class": "", "id": 8068191, "raw_content": "", "author": "Business-Socks", "created": 1758978095149, "profile_picture": "", "community": "TheDonald", "ad_tier": 2, "last_comment_author": "lifeisahologram", "is_video": false, "video_link": "", "is_new_user": false, "domain": "media.patriots.win", "is_crosspost": false, "preview": "https://media.scored.co/preview/1AR0eJ9waf.png", "removal_source": "", "link": "https://media.patriots.win/post/Jh8FLrpjPqxH.jpeg", "author_flair_class": "", "is_removed": false, "media": {"resized_resolutions": [{"reference": "/scale/egxHDF4i3IB3QpIB.jpeg", "width": 614, "content-type": "jpeg", "height": 768}], "blurhash": "UEFr@x%KT}$k0GxVItS%=rxZ-5X9H;Nei]s.", "full_resolution": [900, 720]}, "title": "Press Secretary Karoline Leavitt - we have the best team, don't we folks!", "last_comment_created": 1759011276398, "content": "", "score_down": 4, "author_flair_text": "", "pro_tier": 0, "is_stickied": false, "is_nsfw": false, "is_deleted": false, "is_image": true, "comments": 19, "score_up": 349, "is_edited": false, "is_moderator": false, "awards": 0, "vote_state": 2, "link_metadata": {"status": 200}, "post_flair_text": "", "archive_id": ""}, {"is_locked": false, "tweet_id": "1972070976138760640", "sticky_comment": 0, "is_video_mp4": false, "type": "link", "uuid": "1AR0eKIt8v", "is_twitter": true, "is_admin": false, "score": 56, "suggested_sort": 0, "post_flair_class": "", "id": 8069385, "raw_content": "", "author": "blockchain-the-vote", "created": 1759013579486, "profile_picture": "qNV5Yu864PFJ", "community": "TheDonald", "ad_tier": 2, "last_comment_author": "splink", "is_video": false, "video_link": "", "is_new_user": false, "domain": "twitter.com", "is_crosspost": false, "preview": "https://media.scored.co/preview/1AR0eKIt8v.png", "removal_source": "", "link": "https://twitter.com/StephenM/status/1972070976138760640", "author_flair_class": "", "is_removed": false, "media": {"resized_resolutions": [], "blurhash": "", "full_resolution": []}, "title": "Anyone who looks like the Gov of Oregon should never be allowed near power again, not even the HOA", "last_comment_created": 1759018414964, "content": "", "score_down": 0, "author_flair_text": "", "pro_tier": 0, "is_stickied": false, "is_nsfw": false, "is_deleted": false, "is_image": false, "comments": 6, "score_up": 56, "is_edited": false, "is_moderator": false, "awards": 0, "vote_state": 2, "link_metadata": {"twitter": {"quotedTweet": {"quotedTweet": false, "images": false, "linkEmbed": false, "replies": 0, "created": 1758989761000, "id": "1971972103697322129", "video": false, "poll": false, "user": {"profilePicture": "https://pbs.twimg.com/profile_images/1513357964362629125/r8T2jMvK_normal.jpg", "displayName": "Ron Wyden", "username": "RonWyden"}, "content": "Trump is launching an authoritarian takeover of Portland hoping to provoke conflict in my hometown. I urge Oregonians to reject Trump\u2019s attempt to incite violence in what we know is a vibrant and peaceful city. I will do everything in my power to protect the people in our state.", "parentTweet": false, "likes": 6398}, "images": false, "linkEmbed": false, "replies": 114, "created": 1759013334000, "id": "1972070976138760640", "video": false, "poll": false, "user": {"profilePicture": "https://pbs.twimg.com/profile_images/1364996415731171329/d4WWN4ak_normal.jpg", "displayName": "Stephen Miller", "username": "StephenM"}, "content": "According to a sitting US Senator, if a federal ICE facility and its officers are subjected to unceasing violent antifa terrorism the correct response is for the federal government to unconditionally surrender, withdraw, and suspend enforcement\u2014or face even more antifa violence.", "parentTweet": false, "likes": 1095}}, "post_flair_text": "", "archive_id": ""}, {"is_locked": false, "tweet_id": "1971782819119878349", "sticky_comment": 0, "is_video_mp4": false, "type": "link", "uuid": "1AR0eI3kCC", "is_twitter": true, "is_admin": false, "score": 601, "suggested_sort": 0, "post_flair_class": "", "id": 8067954, "raw_content": "", "author": "dailystreak", "created": 1758966931104, "profile_picture": "", "community": "TheDonald", "ad_tier": 2, "last_comment_author": "RedAltoids", "is_video": false, "video_link": "", "is_new_user": false, "domain": "twitter.com", "is_crosspost": false, "preview": "https://media.scored.co/preview/1AR0eI3kCC.png", "removal_source": "", "link": "https://twitter.com/ElijahSchaffer/status/1971782819119878349", "author_flair_class": "", "is_removed": false, "media": {"resized_resolutions": [], "blurhash": "", "full_resolution": []}, "title": "Elijah Schaffer: I will dedicate my entire life to the America First initiative\n\nThat means resisting authoritarian tyrants like Netanyahu at every corner\n\nHe\u2019s a disgusting shit stain on Western values and cultural excellence \n\nDisgusting anti-Western American tax payer whore\n\nFuck him", "last_comment_created": 1759018065299, "content": "", "score_down": 18, "author_flair_text": "", "pro_tier": 0, "is_stickied": false, "is_nsfw": false, "is_deleted": false, "is_image": false, "comments": 52, "score_up": 619, "is_edited": false, "is_moderator": false, "awards": 0, "vote_state": 2, "link_metadata": {"twitter": {"quotedTweet": {"quotedTweet": false, "images": false, "linkEmbed": false, "replies": 0, "created": 1758942530000, "id": "1971774003724669038", "video": {"preview": "https://pbs.twimg.com/amplify_video_thumb/1971696158595481601/img/B9u_esJB1I6Jfife.jpg", "mpeg": "https://video.twimg.com/amplify_video/1971696158595481601/pl/bOh6n_zEA0YAZbuE.m3u8?v=0b6", "aspectRatio": [9, 16], "heightRatio": 177, "type": "video/mp4", "url": "https://video.twimg.com/amplify_video/1971696158595481601/vid/avc1/320x568/on_O1qGKuifHjG7h.mp4"}, "poll": false, "user": {"profilePicture": "https://pbs.twimg.com/profile_images/1875737644212056064/4iBKXWR6_normal.jpg", "displayName": "Joel Webbon", "username": "rightresponsem"}, "content": "1) Israel buys TikTok. \n\n2) Netanyahu immediately meets with content creators in the U.S. \n\n3) He commissions them to fight against their fellow Americans, in order to secure support for the state of Israel.\n\n*You do not hate Israel enough. \n", "parentTweet": false, "likes": 7620}, "images": false, "linkEmbed": false, "replies": 55, "created": 1758944632000, "id": "1971782819119878349", "video": false, "poll": false, "user": {"profilePicture": "https://pbs.twimg.com/profile_images/1900370091901886464/WjFZMsB__normal.jpg", "displayName": "E", "username": "ElijahSchaffer"}, "content": "I will dedicate my entire life to the America First initiative\n\nThat means resisting authoritarian tyrants like Netanyahu at every corner\n\nHe\u2019s a disgusting shit stain on Western values and cultural excellence \n\nDisgusting anti-Western American tax payer whore\n\nFuck him", "parentTweet": false, "likes": 1032}}, "post_flair_text": "", "archive_id": ""}, {"is_locked": false, "tweet_id": "", "sticky_comment": 0, "is_video_mp4": false, "type": "link", "uuid": "1AR0eJBrrs", "is_twitter": false, "is_admin": false, "score": 105, "suggested_sort": 0, "post_flair_class": "", "id": 8068888, "raw_content": "", "author": "TRUTH_BE_OUR_DOGMA", "created": 1759001020084, "profile_picture": "", "community": "TheDonald", "ad_tier": 2, "last_comment_author": "MakinBacon", "is_video": false, "video_link": "", "is_new_user": false, "domain": "www.thegatewaypundit.com", "is_crosspost": false, "preview": "https://media.scored.co/preview/1AR0eJBrrs.png", "removal_source": "", "link": "https://www.thegatewaypundit.com/2025/09/georgia-state-election-board-votes-subpoena-2020-election/", "author_flair_class": "", "is_removed": false, "media": {"resized_resolutions": [], "blurhash": "", "full_resolution": []}, "title": "Georgia State Election Board Votes to Subpoena 2020 Election Physical Ballots, Envelopes, and Stubs From Fulton County\r\n", "last_comment_created": 1759008139150, "content": "", "score_down": 0, "author_flair_text": "", "pro_tier": 0, "is_stickied": false, "is_nsfw": false, "is_deleted": false, "is_image": false, "comments": 7, "score_up": 105, "is_edited": false, "is_moderator": false, "awards": 0, "vote_state": 2, "link_metadata": {"description": "\u00a0 \u00a0 \u00a0 \u00a0 \u00a0\u00a0\u00a0 Earlier this month, the Gateway Pundit reported that Rep.", "large_image": "99EAA4Bkc13SttOl.png", "title": "Georgia State Election Board Votes to Subpoena 2020 Election Physical Ballots, Envelopes, and Stubs From Fulton County | The Gateway Pundit | by Brian Lupo"}, "post_flair_text": "", "archive_id": ""}, {"is_locked": false, "tweet_id": "", "sticky_comment": 0, "is_video_mp4": false, "type": "link", "uuid": "1AR0eKIKuY", "is_twitter": false, "is_admin": false, "score": 72, "suggested_sort": 0, "post_flair_class": "", "id": 8069162, "raw_content": "", "author": "BidenSniffsLittleKid", "created": 1759008304038, "profile_picture": "oWp1WtRBKa4S", "community": "TheDonald", "ad_tier": 2, "last_comment_author": "RINO_fatigue", "is_video": false, "video_link": "", "is_new_user": false, "domain": "media.patriots.win", "is_crosspost": false, "preview": "https://media.scored.co/preview/1AR0eKIKuY.png", "removal_source": "", "link": "https://media.patriots.win/post/GPanQwcGxEZ6.jpeg", "author_flair_class": "", "is_removed": false, "media": {"resized_resolutions": [{"reference": "/scale/wkxg2rkiC4ByVNiY.jpeg", "width": 731, "content-type": "jpeg", "height": 768}], "blurhash": "U5C$v2xscG%2xwt7R$WV?wR+EKt7#vNao[s;", "full_resolution": [1330, 1266]}, "title": "I DON'T LIKE MY TAX DOLLARS BEING USED TO BLOW UP COUNTRIES ON THE OTHER SIDE OF THE WORLD.", "last_comment_created": 1759014178745, "content": "", "score_down": 2, "author_flair_text": "", "pro_tier": 0, "is_stickied": false, "is_nsfw": false, "is_deleted": false, "is_image": true, "comments": 2, "score_up": 74, "is_edited": false, "is_moderator": false, "awards": 0, "vote_state": 2, "link_metadata": {"status": 200}, "post_flair_text": "", "archive_id": ""}, {"is_locked": false, "tweet_id": "", "sticky_comment": 0, "is_video_mp4": false, "type": "link", "uuid": "1AR0eKJA3g", "is_twitter": false, "is_admin": false, "score": 49, "suggested_sort": 0, "post_flair_class": "", "id": 8069464, "raw_content": "", "author": "WokeYoke", "created": 1759015769661, "profile_picture": "8sWAcGxgUgJ5", "community": "TheDonald", "ad_tier": 2, "last_comment_author": "Coprolite", "is_video": false, "video_link": "", "is_new_user": false, "domain": "media.patriots.win", "is_crosspost": false, "preview": "https://media.scored.co/preview/1AR0eKJA3g.png", "removal_source": "", "link": "https://media.patriots.win/post/60tEZ2o31o0d.jpeg", "author_flair_class": "", "is_removed": false, "media": {"resized_resolutions": [{"reference": "/scale/pvmQAxIri7B3X1rz.jpeg", "width": 571, "content-type": "jpeg", "height": 768}], "blurhash": "UKDu-}O?Vawh}QwcSwkRaQbasTWYJPX5jKep", "full_resolution": [1450, 1079]}, "title": "We Deserve Better PsyOps", "last_comment_created": 1759018216423, "content": "", "score_down": 1, "author_flair_text": "", "pro_tier": 0, "is_stickied": false, "is_nsfw": false, "is_deleted": false, "is_image": true, "comments": 2, "score_up": 50, "is_edited": false, "is_moderator": false, "awards": 0, "vote_state": 2, "link_metadata": {"status": 200}, "post_flair_text": "", "archive_id": ""}, {"is_locked": false, "tweet_id": "", "sticky_comment": 0, "is_video_mp4": false, "type": "link", "uuid": "1AR0eJBaHj", "is_twitter": false, "is_admin": false, "score": 141, "suggested_sort": 0, "post_flair_class": "", "id": 8068703, "raw_content": "", "author": "Lol_Garrus", "created": 1758995066497, "profile_picture": "0257S53ZNysz", "community": "TheDonald", "ad_tier": 2, "last_comment_author": "SupFrens", "is_video": false, "video_link": "", "is_new_user": false, "domain": "media.patriots.win", "is_crosspost": false, "preview": "https://media.scored.co/preview/1AR0eJBaHj.png", "removal_source": "", "link": "https://media.patriots.win/post/F3okRaGIPG5r.jpeg", "author_flair_class": "", "is_removed": false, "media": {"resized_resolutions": [{"reference": "/scale/JKMmuxcRsaGWxjT5.jpeg", "width": 500, "content-type": "jpeg", "height": 739}], "blurhash": "UMGb#oro9aWE05WGx^nzb_wZWrWZ_NM|IWog", "full_resolution": [739, 500]}, "title": "It's really simple.", "last_comment_created": 1758999353323, "content": "", "score_down": 1, "author_flair_text": "", "pro_tier": 0, "is_stickied": false, "is_nsfw": false, "is_deleted": false, "is_image": true, "comments": 1, "score_up": 142, "is_edited": false, "is_moderator": false, "awards": 0, "vote_state": 2, "link_metadata": {"status": 200}, "post_flair_text": "", "archive_id": ""}, {"is_locked": false, "tweet_id": "1972003303556096167", "sticky_comment": 0, "is_video_mp4": false, "type": "link", "uuid": "1AR0eKIt4q", "is_twitter": true, "is_admin": false, "score": 56, "suggested_sort": 0, "post_flair_class": "", "id": 8069378, "raw_content": "", "author": "kinbergfan", "created": 1759013428348, "profile_picture": "", "community": "TheDonald", "ad_tier": 2, "last_comment_author": "IllIllIll", "is_video": false, "video_link": "", "is_new_user": false, "domain": "twitter.com", "is_crosspost": false, "preview": "https://media.scored.co/preview/1AR0eKIt4q.png", "removal_source": "", "link": "https://twitter.com/MarioNawfal/status/1972003303556096167", "author_flair_class": "", "is_removed": false, "media": {"resized_resolutions": [], "blurhash": "", "full_resolution": []}, "title": "INTERVIEW \u2013 MIKE BENZ: \u201c100,000 LEAKED EMAILS TIE ISRAELI PM TO EPSTEIN\u201d\n\nMike Benz reveals a massive leak from former Israeli PM Ehud Barak\u2019s private account, with hundreds of emails directly linked to Jeffrey Epstein.", "last_comment_created": 1759019306182, "content": "", "score_down": 2, "author_flair_text": "", "pro_tier": 0, "is_stickied": false, "is_nsfw": false, "is_deleted": false, "is_image": false, "comments": 8, "score_up": 58, "is_edited": false, "is_moderator": false, "awards": 0, "vote_state": 2, "link_metadata": {"twitter": {"quotedTweet": {"quotedTweet": false, "images": false, "linkEmbed": false, "replies": 0, "created": 1758922800000, "id": "1971691247938031630", "video": {"preview": "https://pbs.twimg.com/amplify_video_thumb/1971681436554948608/img/tJ8F9LlnEuuITq-N.jpg", "mpeg": "https://video.twimg.com/amplify_video/1971681436554948608/pl/m_EF6hxs_DqWTR_9.m3u8?v=86b", "aspectRatio": [16, 9], "heightRatio": 56, "type": "video/mp4", "url": "https://video.twimg.com/amplify_video/1971681436554948608/vid/avc1/480x270/py0E43hmkCdtPMF5.mp4"}, "poll": false, "user": {"profilePicture": "https://pbs.twimg.com/profile_images/1938244629071015936/UwtzYY-R_normal.jpg", "displayName": "Mario Nawfal", "username": "MarioNawfal"}, "content": "\ud83d\udea8\ud83c\uddfa\ud83c\uddf8 MIKE BENZ: \u201cEPSTEIN WAS AN INTELLIGENCE ASSET - AND HE PAID WITH HIS LIFE\u201d\n\nFreshly unsealed Epstein files reveal new names in flight logs and ledgers, raising the stakes even higher.\n\nIn my second interview with @MikeBenzCyber, he explains how he believes Epstein brokered", "parentTweet": false, "likes": 2455}, "images": false, "linkEmbed": false, "replies": 60, "created": 1758997200000, "id": "1972003303556096167", "video": {"preview": "https://pbs.twimg.com/amplify_video_thumb/1971977551422554112/img/tahekjSs080nzN3T.jpg", "mpeg": "https://video.twimg.com/amplify_video/1971977551422554112/pl/dX-VnPYe8ElRLvYa.m3u8?v=e85", "aspectRatio": [16, 9], "heightRatio": 56, "type": "video/mp4", "url": "https://video.twimg.com/amplify_video/1971977551422554112/vid/avc1/480x270/tqpylV5OSd0Em7Nk.mp4"}, "poll": false, "user": {"profilePicture": "https://pbs.twimg.com/profile_images/1938244629071015936/UwtzYY-R_normal.jpg", "displayName": "Mario Nawfal", "username": "MarioNawfal"}, "content": "\ud83c\uddee\ud83c\uddf1 INTERVIEW \u2013 MIKE BENZ: \u201c100,000 LEAKED EMAILS TIE ISRAELI PM TO EPSTEIN\u201d\n\nMike Benz reveals a massive leak from former Israeli PM Ehud Barak\u2019s private account, with hundreds of emails directly linked to Jeffrey Epstein.\n\n@MikeBenzCyber:\n\n\u201cWhat just leaked online were about", "parentTweet": false, "likes": 2022}}, "post_flair_text": "", "archive_id": ""}, {"is_locked": false, "tweet_id": "", "sticky_comment": 0, "is_video_mp4": false, "type": "link", "uuid": "1AR0eKJABx", "is_twitter": false, "is_admin": false, "score": 47, "suggested_sort": 0, "post_flair_class": "", "id": 8069485, "raw_content": "", "author": "Trick", "created": 1759016410753, "profile_picture": "", "community": "TheDonald", "ad_tier": 2, "last_comment_author": "", "is_video": false, "video_link": "", "is_new_user": false, "domain": "townhall.com", "is_crosspost": false, "preview": "https://media.scored.co/preview/1AR0eKJABx.png", "removal_source": "", "link": "https://townhall.com/tipsheet/scott-mcclallen/2025/09/27/three-women-indicted-for-doxxing-ice-agent-after-livestreamed-pursuit-n2664080", "author_flair_class": "", "is_removed": false, "media": {"resized_resolutions": [], "blurhash": "", "full_resolution": []}, "title": "Jury Indict Women Who Hunted ICE Agent and Posted His Address Online", "last_comment_created": 1759016410753, "content": "", "score_down": 0, "author_flair_text": "", "pro_tier": 0, "is_stickied": false, "is_nsfw": false, "is_deleted": false, "is_image": false, "comments": 0, "score_up": 47, "is_edited": false, "is_moderator": false, "awards": 0, "vote_state": 2, "link_metadata": {"description": "Three women indicted for doxxing an ICE agent after a livestreamed pursuit.", "large_image": "KgS9wwmSZGxS4XIx.png", "title": "Jury Indict Women Who Hunted ICE Agent and Posted His Address Online"}, "post_flair_text": "", "archive_id": ""}, {"is_locked": false, "tweet_id": "1971945880384348223", "sticky_comment": 0, "is_video_mp4": false, "type": "link", "uuid": "1AR0eJC8S0", "is_twitter": true, "is_admin": false, "score": 97, "suggested_sort": 0, "post_flair_class": "", "id": 8068918, "raw_content": "", "author": "ALT26", "created": 1759002181954, "profile_picture": "", "community": "TheDonald", "ad_tier": 2, "last_comment_author": "HOSEQ", "is_video": false, "video_link": "", "is_new_user": false, "domain": "twitter.com", "is_crosspost": false, "preview": "https://media.scored.co/preview/1AR0eJC8S0.png", "removal_source": "", "link": "https://twitter.com/Cernovich/status/1971945880384348223", "author_flair_class": "", "is_removed": false, "media": {"resized_resolutions": [], "blurhash": "", "full_resolution": []}, "title": "The SPLC is a terrorist cell.\n", "last_comment_created": 1759008606160, "content": "", "score_down": 0, "author_flair_text": "", "pro_tier": 0, "is_stickied": false, "is_nsfw": false, "is_deleted": false, "is_image": false, "comments": 1, "score_up": 97, "is_edited": false, "is_moderator": false, "awards": 0, "vote_state": 2, "link_metadata": {"twitter": {"quotedTweet": {"quotedTweet": false, "images": [{"width": 1250, "heightRatio": 52, "url": "https://pbs.twimg.com/media/G1dHMTlXsAAOxI8.jpg", "height": 650}], "linkEmbed": false, "replies": 0, "created": 1758550230000, "id": "1970128578361659822", "video": false, "poll": false, "user": {"profilePicture": "https://pbs.twimg.com/profile_images/1928613478392057856/TuzHfqhm_normal.jpg", "displayName": "Tyler O'Neil", "username": "Tyler2ONeil"}, "content": "\ud83d\udea8DISTURBING TIES\n\nThe Southern Poverty Law Center, which put Turning Point USA on a \"hate map\" with chapters of the Ku Klux Klan a few months before Kirk's assassination, has disturbing connections to Antifa.\n\nThese are quite relevant as Trump investigates Antifa.\n\n\ud83e\uddf51/12", "parentTweet": false, "likes": 15459}, "images": false, "linkEmbed": false, "replies": 32, "created": 1758983509000, "id": "1971945880384348223", "video": false, "poll": false, "user": {"profilePicture": "https://pbs.twimg.com/profile_images/1891619729879801856/QofbmzaO_normal.jpg", "displayName": "Cernovich", "username": "Cernovich"}, "content": "The SPLC is a terrorist cell.", "parentTweet": false, "likes": 2427}}, "post_flair_text": "", "archive_id": ""}, {"is_locked": false, "tweet_id": "", "sticky_comment": 0, "is_video_mp4": false, "type": "link", "uuid": "1AR0eKI3ve", "is_twitter": false, "is_admin": false, "score": 77, "suggested_sort": 0, "post_flair_class": "", "id": 8069072, "raw_content": "", "author": "Beat_to_Quarters", "created": 1759006677814, "profile_picture": "", "community": "TheDonald", "ad_tier": 2, "last_comment_author": "Lurkermon", "is_video": false, "video_link": "", "is_new_user": false, "domain": "media.scored.co", "is_crosspost": false, "preview": "https://media.scored.co/preview/1AR0eKI3ve.png", "removal_source": "", "link": "https://media.scored.co/post/JOk8GpEbHcCA.jpeg", "author_flair_class": "", "is_removed": false, "media": {"resized_resolutions": [{"reference": "/scale/1ElpboE3eW65yNtS.jpeg", "width": 577, "content-type": "jpeg", "height": 768}], "blurhash": "UQJRaOxut7og00xuRjay~qM{M{WB4nWAxuof", "full_resolution": [958, 720]}, "title": "Kind of revealing that FBI agents are BLM protesters while wearing their FBI gear, but are J6 protesters while being undercover. ", "last_comment_created": 1759011743690, "content": "", "score_down": 0, "author_flair_text": "", "pro_tier": 0, "is_stickied": false, "is_nsfw": false, "is_deleted": false, "is_image": true, "comments": 8, "score_up": 77, "is_edited": false, "is_moderator": false, "awards": 0, "vote_state": 2, "link_metadata": {"status": 200}, "post_flair_text": "", "archive_id": ""}, {"is_locked": false, "tweet_id": "", "sticky_comment": 0, "is_video_mp4": false, "type": "link", "uuid": "1AR0eI3jzo", "is_twitter": false, "is_admin": false, "score": 637, "suggested_sort": 0, "post_flair_class": "", "id": 8067924, "raw_content": "", "author": "MickHigan2", "created": 1758965343146, "profile_picture": "mxiq4uyPJ852", "community": "TheDonald", "ad_tier": 2, "last_comment_author": "Saltish", "is_video": false, "video_link": "", "is_new_user": false, "domain": "media.scored.co", "is_crosspost": false, "preview": "https://media.scored.co/preview/1AR0eI3jzo.png", "removal_source": "", "link": "https://media.scored.co/post/1z5GQOeKykpn.jpeg", "author_flair_class": "", "is_removed": false, "media": {"resized_resolutions": [{"reference": "/scale/fuHV5vGzJYk6MXK5.jpeg", "width": 768, "content-type": "jpeg", "height": 287}], "blurhash": "UB8XRe~L.7s*EVDiSRoHxt$_%MV@-pxuV@ja", "full_resolution": [397, 1064]}, "title": "All of them need to go\n", "last_comment_created": 1759018023203, "content": "", "score_down": 1, "author_flair_text": "", "pro_tier": 0, "is_stickied": false, "is_nsfw": false, "is_deleted": false, "is_image": true, "comments": 33, "score_up": 638, "is_edited": false, "is_moderator": false, "awards": 0, "vote_state": 2, "link_metadata": {"status": 200}, "post_flair_text": "", "archive_id": ""}, {"is_locked": false, "tweet_id": "1972005867580281038", "sticky_comment": 0, "is_video_mp4": false, "type": "link", "uuid": "1AR0eJBrOw", "is_twitter": true, "is_admin": false, "score": 117, "suggested_sort": 0, "post_flair_class": "", "id": 8068816, "raw_content": "", "author": "rdvs34283", "created": 1758998517251, "profile_picture": "cPYPv2FTjaqs", "community": "TheDonald", "ad_tier": 2, "last_comment_author": "Turd_Ferguson", "is_video": false, "video_link": "", "is_new_user": false, "domain": "twitter.com", "is_crosspost": false, "preview": "https://media.scored.co/preview/1AR0eJBrOw.png", "removal_source": "", "link": "https://twitter.com/elonmusk/status/1972005867580281038", "author_flair_class": "", "is_removed": false, "media": {"resized_resolutions": [], "blurhash": "", "full_resolution": []}, "title": "Elon Musk highlights Fake News Media", "last_comment_created": 1759003925877, "content": "", "score_down": 1, "author_flair_text": "", "pro_tier": 0, "is_stickied": false, "is_nsfw": false, "is_deleted": false, "is_image": false, "comments": 1, "score_up": 118, "is_edited": false, "is_moderator": false, "awards": 0, "vote_state": 2, "link_metadata": {"twitter": {"quotedTweet": {"quotedTweet": false, "images": false, "linkEmbed": false, "replies": 0, "created": 1758913262000, "id": "1971651242939318303", "video": false, "poll": false, "user": {"profilePicture": "https://pbs.twimg.com/profile_images/1604907328242962433/P_79at43_normal.jpg", "displayName": "Sky News", "username": "SkyNews"}, "content": "Elon Musk and Prince Andrew named in latest Epstein files release\n", "parentTweet": false, "likes": 33739}, "images": false, "linkEmbed": false, "replies": 2142, "created": 1758997811000, "id": "1972005867580281038", "video": false, "poll": false, "user": {"profilePicture": "https://pbs.twimg.com/profile_images/1936002956333080576/kqqe2iWO_normal.jpg", "displayName": "Elon Musk", "username": "elonmusk"}, "content": "Shame on Sky News for this utterly misleading headline. Anyone pushing this false narrative deserves complete contempt. \n\nEpstein tried to get me to go to his island and I REFUSED, yet they name me even before Prince Andrew, who did visit.", "parentTweet": false, "likes": 11354}}, "post_flair_text": "", "archive_id": ""}, {"is_locked": false, "tweet_id": "1972005357418696828", "sticky_comment": 0, "is_video_mp4": false, "type": "link", "uuid": "1AR0eKJQuI", "is_twitter": true, "is_admin": false, "score": 43, "suggested_sort": 0, "post_flair_class": "", "id": 8069532, "raw_content": "", "author": "rdvs34283", "created": 1759017852452, "profile_picture": "cPYPv2FTjaqs", "community": "TheDonald", "ad_tier": 2, "last_comment_author": "brutustyberius", "is_video": false, "video_link": "", "is_new_user": false, "domain": "twitter.com", "is_crosspost": false, "preview": "https://media.scored.co/preview/1AR0eKJQuI.png", "removal_source": "", "link": "https://twitter.com/c_3c_3/status/1972005357418696828", "author_flair_class": "", "is_removed": false, "media": {"resized_resolutions": [], "blurhash": "", "full_resolution": []}, "title": "Find out who this is and January 6th crumbles.", "last_comment_created": 1759022344848, "content": "", "score_down": 0, "author_flair_text": "", "pro_tier": 0, "is_stickied": false, "is_nsfw": false, "is_deleted": false, "is_image": false, "comments": 6, "score_up": 43, "is_edited": false, "is_moderator": false, "awards": 0, "vote_state": 2, "link_metadata": {"twitter": {"quotedTweet": false, "images": [{"width": 540, "heightRatio": 146, "url": "https://pbs.twimg.com/media/G134a7EXoAAg8qq.jpg", "height": 789}], "linkEmbed": false, "replies": 530, "created": 1758997689000, "id": "1972005357418696828", "video": false, "poll": false, "user": {"profilePicture": "https://pbs.twimg.com/profile_images/945294827742224385/2g_sshAu_normal.jpg", "displayName": "C3", "username": "C_3C_3"}, "content": "Find out who this is and January 6th crumbles.", "parentTweet": false, "likes": 11455}}, "post_flair_text": "", "archive_id": ""}, {"is_locked": false, "tweet_id": "", "sticky_comment": 0, "is_video_mp4": false, "type": "link", "uuid": "1AR0eI3kOW", "is_twitter": false, "is_admin": false, "score": 514, "suggested_sort": 0, "post_flair_class": "", "id": 8067980, "raw_content": "", "author": "rdvs34283", "created": 1758968868015, "profile_picture": "cPYPv2FTjaqs", "community": "TheDonald", "ad_tier": 2, "last_comment_author": "cyberrigger", "is_video": false, "video_link": "", "is_new_user": false, "domain": "www.thegatewaypundit.com", "is_crosspost": false, "preview": "https://media.scored.co/preview/1AR0eI3kOW.png", "removal_source": "", "link": "https://www.thegatewaypundit.com/2025/09/southern-states-mississippi-louisiana-go-back-teaching-basics/", "author_flair_class": "", "is_removed": false, "media": {"resized_resolutions": [], "blurhash": "", "full_resolution": []}, "title": "Southern States of Mississippi and Louisiana Go Back to Teaching the Basics in School \u2013 Now Lead Liberal States Like California in Literacy", "last_comment_created": 1758992232712, "content": "", "score_down": 0, "author_flair_text": "", "pro_tier": 0, "is_stickied": false, "is_nsfw": false, "is_deleted": false, "is_image": false, "comments": 13, "score_up": 514, "is_edited": false, "is_moderator": false, "awards": 0, "vote_state": 2, "link_metadata": {"description": "\u00a0 \u00a0 \u00a0 \u00a0 \u00a0\u00a0Anyone who follows education news, or just has children in public schools, knows that we have an education crisis in this country right now.", "large_image": "Po7kjp6My6E3L46T.png", "title": "Southern States of Mississippi and Louisiana Go Back to Teaching the Basics in School - Now Lead Liberal States Like California in Literacy | The Gateway Pundit | by Mike LaChance"}, "post_flair_text": "", "archive_id": ""}, {"is_locked": false, "tweet_id": "", "sticky_comment": 0, "is_video_mp4": false, "type": "link", "uuid": "1AR0eJC8eP", "is_twitter": false, "is_admin": false, "score": 91, "suggested_sort": 0, "post_flair_class": "", "id": 8068949, "raw_content": "", "author": "12345SIX", "created": 1759002887584, "profile_picture": "", "community": "TheDonald", "ad_tier": 2, "last_comment_author": "JustInTime2_", "is_video": false, "video_link": "", "is_new_user": false, "domain": "media.scored.co", "is_crosspost": false, "preview": "https://media.scored.co/preview/1AR0eJC8eP.png", "removal_source": "", "link": "https://media.scored.co/post/HdvdhI3NonhI.jpeg", "author_flair_class": "", "is_removed": false, "media": {"resized_resolutions": [{"reference": "/scale/wGx9v9N5JAc2e33q.png", "width": 768, "content-type": "png", "height": 381}], "blurhash": "U3P%V500%L00~VWCWCox~Vxai^xt~qNGIpxZ", "full_resolution": [635, 1280]}, "title": "\nOH JUST STOP IT! JEWS ARENT TRYING TO TAKE OVER THE UNITED STATES!!", "last_comment_created": 1759016243167, "content": "", "score_down": 3, "author_flair_text": "", "pro_tier": 0, "is_stickied": false, "is_nsfw": false, "is_deleted": false, "is_image": true, "comments": 13, "score_up": 94, "is_edited": false, "is_moderator": false, "awards": 0, "vote_state": 2, "link_metadata": {"status": 200}, "post_flair_text": "", "archive_id": ""}, {"is_locked": false, "tweet_id": "1972019942813061128", "sticky_comment": 0, "is_video_mp4": false, "type": "link", "uuid": "1AR0eKItD3", "is_twitter": true, "is_admin": false, "score": 52, "suggested_sort": 0, "post_flair_class": "", "id": 8069395, "raw_content": "", "author": "FuckAllDemocrats", "created": 1759013915225, "profile_picture": "", "community": "TheDonald", "ad_tier": 2, "last_comment_author": "Filo76", "is_video": false, "video_link": "", "is_new_user": false, "domain": "twitter.com", "is_crosspost": false, "preview": "https://media.scored.co/preview/1AR0eKItD3.png", "removal_source": "", "link": "https://twitter.com/grandoldmemes/status/1972019942813061128?s=46&t=eC-6bvibHP_gKJ9ZlbrhfA", "author_flair_class": "", "is_removed": false, "media": {"resized_resolutions": [], "blurhash": "", "full_resolution": []}, "title": "Fatter of 2 Williams sisters goes ballistic over cotton fake flower", "last_comment_created": 1759019747022, "content": "", "score_down": 0, "author_flair_text": "", "pro_tier": 0, "is_stickied": false, "is_nsfw": false, "is_deleted": false, "is_image": false, "comments": 2, "score_up": 52, "is_edited": false, "is_moderator": false, "awards": 0, "vote_state": 2, "link_metadata": {"twitter": {"quotedTweet": false, "images": [{"width": 1024, "heightRatio": 150, "url": "https://pbs.twimg.com/media/G14Fr93WEAA8PhA.jpg", "height": 1536}], "linkEmbed": false, "replies": 239, "created": 1759001167000, "id": "1972019942813061128", "video": false, "poll": false, "user": {"profilePicture": "https://pbs.twimg.com/profile_images/1401344279520464898/1UzVSHes_normal.jpg", "displayName": "The Right To Bear Memes", "username": "grandoldmemes"}, "content": "", "parentTweet": false, "likes": 7719}}, "post_flair_text": "", "archive_id": ""}, {"is_locked": false, "tweet_id": "1971735109826236635", "sticky_comment": 0, "is_video_mp4": false, "type": "link", "uuid": "1AR0eJBJIo", "is_twitter": true, "is_admin": false, "score": 155, "suggested_sort": 0, "post_flair_class": "geotus", "id": 8068612, "raw_content": "", "author": "SuperHonkey", "created": 1758991908702, "profile_picture": "4D2pFXGQIC6T", "community": "TheDonald", "ad_tier": 2, "last_comment_author": "Talon54", "is_video": false, "video_link": "", "is_new_user": false, "domain": "twitter.com", "is_crosspost": false, "preview": "https://media.scored.co/preview/1AR0eJBJIo.png", "removal_source": "", "link": "https://twitter.com/IndianaGPA/status/1971735109826236635", "author_flair_class": "", "is_removed": false, "media": {"resized_resolutions": [], "blurhash": "", "full_resolution": []}, "title": "Shitposter-in-Chief \ud83e\udd23", "last_comment_created": 1759007699912, "content": "", "score_down": 1, "author_flair_text": "", "pro_tier": 0, "is_stickied": false, "is_nsfw": false, "is_deleted": false, "is_image": false, "comments": 7, "score_up": 156, "is_edited": false, "is_moderator": false, "awards": 0, "vote_state": 2, "link_metadata": {"twitter": {"quotedTweet": false, "images": false, "linkEmbed": false, "replies": 555, "created": 1758933257000, "id": "1971735109826236635", "video": {"preview": "https://pbs.twimg.com/amplify_video_thumb/1971735048614182913/img/zuZ2ovnEVWRS0AfI.jpg", "mpeg": "https://video.twimg.com/amplify_video/1971735048614182913/pl/o5CMsaNB6DyZedEM.m3u8?v=c2d", "aspectRatio": [71, 40], "heightRatio": 56, "type": "video/mp4", "url": "https://video.twimg.com/amplify_video/1971735048614182913/vid/avc1/478x270/BprTAN6KzUaWZ1e5.mp4"}, "poll": false, "user": {"profilePicture": "https://pbs.twimg.com/profile_images/1961748601136115712/RKUu4dCs_normal.jpg", "displayName": "G-PA", "username": "IndianaGPA"}, "content": "Funniest thing I've heard all day \ud83e\udd23\ud83e\udd23 Now that's the President we voted for! God bless him \ud83d\ude4f", "parentTweet": false, "likes": 32262}}, "post_flair_text": "\u00a0\u00a0\u00a0\u00a0GEOTUS \u00a0\u00a0\u00a0\u00a0\u00a0\u00a0\u00a0\u00a0\u00a0\u00a0\u00a0\u00a0", "archive_id": ""}, {"is_locked": false, "tweet_id": "", "sticky_comment": 0, "is_video_mp4": false, "type": "text", "uuid": "1AR0eKJ9zc", "is_twitter": false, "is_admin": false, "score": 46, "suggested_sort": 0, "post_flair_class": "", "id": 8069458, "raw_content": "Muslims the world over are rejoicing as their brothers are put up in nice hotels, given priority in free government housing, receive cash benefits, and don't have to work.\n\nMeanwhile, the police all but ignore rape gangs while arresting British citizens for offensive memes.\n\nCivil war is very possible.  Unfortunately, because Muslims have been so heavily favored thus far, no one knows which side the government will take.", "author": "KuzoKevin", "created": 1759015643502, "profile_picture": "", "community": "TheDonald", "ad_tier": 2, "last_comment_author": "LibsRcrazy", "is_video": false, "video_link": "", "is_new_user": false, "domain": "", "is_crosspost": false, "preview": "", "removal_source": "", "link": "", "author_flair_class": "", "is_removed": false, "media": {"resized_resolutions": [], "blurhash": "", "full_resolution": []}, "title": "Keir Starmer is a disgrace to Great Britain.", "last_comment_created": 1759020560568, "content": "<p>Muslims the world over are rejoicing as their brothers are put up in nice hotels, given priority in free government housing, receive cash benefits, and don't have to work.</p>\n<p>Meanwhile, the police all but ignore rape gangs while arresting British citizens for offensive memes.</p>\n<p>Civil war is very possible.  Unfortunately, because Muslims have been so heavily favored thus far, no one knows which side the government will take.</p>\n", "score_down": 0, "author_flair_text": "", "pro_tier": 0, "is_stickied": false, "is_nsfw": false, "is_deleted": false, "is_image": false, "comments": 5, "score_up": 46, "is_edited": false, "is_moderator": false, "awards": 0, "vote_state": 2, "link_metadata": {"status": 200}, "post_flair_text": "", "archive_id": ""}, {"is_locked": false, "tweet_id": "", "sticky_comment": 0, "is_video_mp4": false, "type": "link", "uuid": "1AR0eI3kOe", "is_twitter": false, "is_admin": false, "score": 492, "suggested_sort": 0, "post_flair_class": "", "id": 8067988, "raw_content": "", "author": "rdvs34283", "created": 1758969163636, "profile_picture": "cPYPv2FTjaqs", "community": "TheDonald", "ad_tier": 2, "last_comment_author": "patrioticwinning3", "is_video": false, "video_link": "", "is_new_user": false, "domain": "www.thegatewaypundit.com", "is_crosspost": false, "preview": "https://media.scored.co/preview/1AR0eI3kOe.png", "removal_source": "", "link": "https://www.thegatewaypundit.com/2025/09/trump-asks-supreme-court-end-birthright-citizenship/", "author_flair_class": "", "is_removed": false, "media": {"resized_resolutions": [], "blurhash": "", "full_resolution": []}, "title": "President Trump Asks Supreme Court to End Birthright Citizenship. Several federal district judges have blocked President Trump\u2019s birthright citizenship executive order. \"Fourteenth Amendment has never been interpreted to extend citizenship universally to everyone born within the U.S.\"", "last_comment_created": 1758991008964, "content": "", "score_down": 0, "author_flair_text": "", "pro_tier": 0, "is_stickied": false, "is_nsfw": false, "is_deleted": false, "is_image": false, "comments": 3, "score_up": 492, "is_edited": false, "is_moderator": false, "awards": 0, "vote_state": 2, "link_metadata": {"description": "\u00a0 \u00a0 \u00a0 \u00a0 \u00a0\u00a0President Trump on Friday asked the US Supreme Court to end birthright citizenship.", "large_image": "hsmAREDIhQFNKeH1.png", "title": "JUST IN: President Trump Asks Supreme Court to End Birthright Citizenship | The Gateway Pundit | by Cristina Laila"}, "post_flair_text": "", "archive_id": ""}, {"is_locked": false, "tweet_id": "", "sticky_comment": 0, "is_video_mp4": false, "type": "link", "uuid": "1AR0eKJ9nE", "is_twitter": false, "is_admin": false, "score": 47, "suggested_sort": 0, "post_flair_class": "", "id": 8069428, "raw_content": "", "author": "blockchain-the-vote", "created": 1759014907977, "profile_picture": "qNV5Yu864PFJ", "community": "TheDonald", "ad_tier": 2, "last_comment_author": "blitzkrieg1", "is_video": false, "video_link": "", "is_new_user": false, "domain": "media.scored.co", "is_crosspost": false, "preview": "https://media.scored.co/preview/1AR0eKJ9nE.png", "removal_source": "", "link": "https://media.scored.co/post/1V9lMTmrD5FY.jpeg", "author_flair_class": "", "is_removed": false, "media": {"resized_resolutions": [{"reference": "/scale/iBYwBBSzJmcHeQJe.png", "width": 768, "content-type": "png", "height": 727}], "blurhash": "UKHC7l?ZaIs,00t5s:of~oRPx^kD00t6M|WE", "full_resolution": [969, 1024]}, "title": "soon", "last_comment_created": 1759020155372, "content": "", "score_down": 0, "author_flair_text": "", "pro_tier": 0, "is_stickied": false, "is_nsfw": false, "is_deleted": false, "is_image": true, "comments": 1, "score_up": 47, "is_edited": false, "is_moderator": false, "awards": 0, "vote_state": 2, "link_metadata": {"status": 200}, "post_flair_text": "", "archive_id": ""}, {"is_locked": false, "tweet_id": "", "sticky_comment": 0, "is_video_mp4": false, "type": "link", "uuid": "1AR0eKJ9vS", "is_twitter": false, "is_admin": false, "score": 46, "suggested_sort": 0, "post_flair_class": "", "id": 8069446, "raw_content": "", "author": "TateDemarcus", "created": 1759015298101, "profile_picture": "", "community": "TheDonald", "ad_tier": 2, "last_comment_author": "", "is_video": false, "video_link": "", "is_new_user": false, "domain": "www.thegatewaypundit.com", "is_crosspost": false, "preview": "https://media.scored.co/preview/1AR0eKJ9vS.png", "removal_source": "", "link": "https://www.thegatewaypundit.com/2025/09/white-house-releases-list-political-agitators-blames-democrats/", "author_flair_class": "", "is_removed": false, "media": {"resized_resolutions": [], "blurhash": "", "full_resolution": []}, "title": "THE WHITE HOUSE RELEASES LIST OF POLITICAL AGITATORS \u2014 Blames Democrats\u2019 \u201cGestapo\u201d Rhetoric for Dallas ICE Attack and 1,000% Surge in Assaults on Federal Agents", "last_comment_created": 1759015298101, "content": "", "score_down": 0, "author_flair_text": "", "pro_tier": 0, "is_stickied": false, "is_nsfw": false, "is_deleted": false, "is_image": false, "comments": 0, "score_up": 46, "is_edited": false, "is_moderator": false, "awards": 0, "vote_state": 2, "link_metadata": {"description": "\u00a0 \u00a0 \u00a0 \u00a0 \u00a0\u00a0The White House on Friday published an article naming more than two dozen prominent Democrat officials as political agitators, accusing them of fanning the flames of domestic violence through \u201cGestapo-style\u201d rhetoric.", "large_image": "DyXUMLu0Nhr6taBt.png", "title": "THE WHITE HOUSE RELEASES LIST OF POLITICAL AGITATORS \u2014 Blames Democrats\u2019 \u201cGestapo\u201d Rhetoric for Dallas ICE Attack and 1,000% Surge in Assaults on Federal Agents | The Gateway Pundit | by Jim H\u1d0fft"}, "post_flair_text": "", "archive_id": ""}], "status": true}