{"has_more_entries": true, "subscriptions": "", "error": "", "posts": [{"is_locked": false, "tweet_id": "", "sticky_comment": 0, "is_video_mp4": false, "type": "link", "uuid": "1ARws2L85b", "is_twitter": false, "is_admin": false, "score": 71, "suggested_sort": 0, "post_flair_class": "", "id": 8380723, "raw_content": "", "author": "spinometer2", "created": 1769734829270, "profile_picture": "", "community": "TheDonald", "ad_tier": 2, "last_comment_author": "CommieCrats", "is_video": false, "video_link": "", "is_new_user": false, "domain": "media.scored.co", "is_crosspost": false, "preview": "https://media.scored.co/preview/1ARws2L85b.png", "removal_source": "", "link": "https://media.scored.co/post/rCFDiRyN4th8.jpeg", "author_flair_class": "", "is_removed": false, "media": {"resized_resolutions": [{"reference": "/scale/sQnIbCOLm9r4e4RA.jpeg", "width": 768, "content-type": "jpeg", "height": 673}], "blurhash": "UhPsec%MxvozRPofj]fk_NIAM{RjXSV@jZWB", "full_resolution": [947, 1080]}, "title": "Breaking: Alex Jones eaten by goblins!", "last_comment_created": 1769746394294, "content": "", "score_down": 2, "author_flair_text": "", "pro_tier": 0, "is_stickied": false, "is_nsfw": false, "is_deleted": false, "is_image": true, "comments": 13, "score_up": 73, "is_edited": false, "is_moderator": false, "awards": 0, "vote_state": 2, "link_metadata": {"status": 200}, "post_flair_text": "", "archive_id": ""}, {"is_locked": false, "tweet_id": "", "sticky_comment": 0, "is_video_mp4": false, "type": "link", "uuid": "1ARws2LPPE", "is_twitter": false, "is_admin": false, "score": 56, "suggested_sort": 0, "post_flair_class": "", "id": 8380868, "raw_content": "", "author": "sum1else", "created": 1769739480354, "profile_picture": "CKzHohj5Ftt5", "community": "TheDonald", "ad_tier": 2, "last_comment_author": "sum1else", "is_video": false, "video_link": "", "is_new_user": false, "domain": "media.scored.co", "is_crosspost": false, "preview": "https://media.scored.co/preview/1ARws2LPPE.png", "removal_source": "", "link": "https://media.scored.co/post/GCmGLxTb5dsJ.jpeg", "author_flair_class": "", "is_removed": false, "media": {"resized_resolutions": [{"reference": "/scale/te67aElOOkPrPaC6.png", "width": 768, "content-type": "png", "height": 515}], "blurhash": "U;Kd#saxWUoL%MWBjtj[~qayoLWVWBt6bHWB", "full_resolution": [582, 868]}, "title": "Maybe this is why the Democrats caved on the shutdown", "last_comment_created": 1769739545394, "content": "", "score_down": 0, "author_flair_text": "", "pro_tier": 0, "is_stickied": false, "is_nsfw": false, "is_deleted": false, "is_image": true, "comments": 1, "score_up": 56, "is_edited": false, "is_moderator": false, "awards": 0, "vote_state": 2, "link_metadata": {"status": 200}, "post_flair_text": "", "archive_id": ""}, {"is_locked": false, "tweet_id": "2016654772699279623", "sticky_comment": 0, "is_video_mp4": false, "type": "link", "uuid": "1ARwnVrWR0", "is_twitter": true, "is_admin": false, "score": 1026, "suggested_sort": 0, "post_flair_class": "", "id": 8379052, "raw_content": "", "author": "PiratePatriotParrot", "created": 1769682583680, "profile_picture": "", "community": "TheDonald", "ad_tier": 2, "last_comment_author": "Amway", "is_video": false, "video_link": "", "is_new_user": false, "domain": "twitter.com", "is_crosspost": false, "preview": "https://media.scored.co/preview/1ARwnVrWR0.png", "removal_source": "", "link": "https://twitter.com/i/status/2016654772699279623", "author_flair_class": "", "is_removed": false, "media": {"resized_resolutions": [], "blurhash": "", "full_resolution": []}, "title": "Can\u2019t make this up. \r\n\r\nThe EU fined X \u20ac45 million after concluding people would think Donald Duck was a real person. \r\n", "last_comment_created": 1769716328515, "content": "", "score_down": 3, "author_flair_text": "", "pro_tier": 0, "is_stickied": false, "is_nsfw": false, "is_deleted": false, "is_image": false, "comments": 73, "score_up": 1029, "is_edited": false, "is_moderator": false, "awards": 0, "vote_state": 2, "link_metadata": {"twitter": {"quotedTweet": {"quotedTweet": false, "images": [{"width": 510, "heightRatio": 114, "url": "https://pbs.twimg.com/media/G_xfKxdXgAAU9oZ.png", "height": 585}], "linkEmbed": false, "replies": 0, "created": 1769634592000, "id": "2016619761891676278", "video": false, "poll": false, "user": {"profilePicture": "https://pbs.twimg.com/profile_images/2014133146711662592/clFOmQDR_normal.jpg", "displayName": "House Judiciary GOP \ud83c\uddfa\ud83c\uddf8\ud83c\uddfa\ud83c\uddf8\ud83c\uddfa\ud83c\uddf8", "username": "JudiciaryGOP"}, "content": "The Commission even gave an example of what it found so objectionable: a blue checkmark on a Donald Duck parody account.\n\nIt called the practice \u201cdeceptive.\u201d\n\nThat\u2019s right\u2014the Commission fined X \u20ac45 million because its practices might lead users to believe that 1) this fictional", "parentTweet": false, "likes": 2978}, "images": false, "linkEmbed": false, "replies": 483, "created": 1769642940000, "id": "2016654772699279623", "video": false, "poll": false, "user": {"profilePicture": "https://pbs.twimg.com/profile_images/2014133146711662592/clFOmQDR_normal.jpg", "displayName": "House Judiciary GOP \ud83c\uddfa\ud83c\uddf8\ud83c\uddfa\ud83c\uddf8\ud83c\uddfa\ud83c\uddf8", "username": "JudiciaryGOP"}, "content": "Can\u2019t make this up. \n\nThe EU fined X \u20ac45 million after concluding people would think Donald Duck was a real person. \n\nGive me a break.", "parentTweet": false, "likes": 7069}}, "post_flair_text": "", "archive_id": ""}, {"is_locked": false, "tweet_id": "", "sticky_comment": 0, "is_video_mp4": false, "type": "link", "uuid": "1ARws3RbKk", "is_twitter": false, "is_admin": false, "score": 45, "suggested_sort": 0, "post_flair_class": "", "id": 8381032, "raw_content": "", "author": "Colorado-Living", "created": 1769743705360, "profile_picture": "", "community": "TheDonald", "ad_tier": 2, "last_comment_author": "MamaLlama2pointOh", "is_video": false, "video_link": "", "is_new_user": false, "domain": "www.12news.com", "is_crosspost": false, "preview": "https://media.scored.co/preview/1ARws3RbKk.png", "removal_source": "", "link": "https://www.12news.com/article/news/politics/immigration-news/ice-purchases-warehouse-west-valley-size-of-seven-football-fields/75-9700f4f7-5f83-4d97-b44a-5af1dd13dafe", "author_flair_class": "", "is_removed": false, "media": {"resized_resolutions": [], "blurhash": "", "full_resolution": []}, "title": "The real Super Bowl:  ICE purchases warehouse in West Valley the size of seven football fields", "last_comment_created": 1769748993898, "content": "", "score_down": 0, "author_flair_text": "", "pro_tier": 0, "is_stickied": false, "is_nsfw": false, "is_deleted": false, "is_image": false, "comments": 5, "score_up": 45, "is_edited": false, "is_moderator": false, "awards": 0, "vote_state": 2, "link_metadata": {"description": "", "large_image": "yugdHysWliMPzc2r.png", "title": "ICE purchases warehouse in West Valley the size of seven football fields"}, "post_flair_text": "", "archive_id": ""}, {"is_locked": false, "tweet_id": "2013413792890180093", "sticky_comment": 0, "is_video_mp4": false, "type": "link", "uuid": "1ARwnVsclM", "is_twitter": true, "is_admin": false, "score": 448, "suggested_sort": 0, "post_flair_class": "", "id": 8379470, "raw_content": "", "author": "MickHigan2", "created": 1769698729371, "profile_picture": "mxiq4uyPJ852", "community": "TheDonald", "ad_tier": 2, "last_comment_author": "thelastlast", "is_video": false, "video_link": "", "is_new_user": false, "domain": "twitter.com", "is_crosspost": false, "preview": "https://media.scored.co/preview/1ARwnVsclM.png", "removal_source": "", "link": "https://twitter.com/i/status/2013413792890180093", "author_flair_class": "", "is_removed": false, "media": {"resized_resolutions": [], "blurhash": "", "full_resolution": []}, "title": "TIL a guy named \"TheGuardRailGuy\" has been on a mission to find bad installations of guard rails because he lost his daughter to an improperly installed one some time back. Patriot. ", "last_comment_created": 1769746388544, "content": "", "score_down": 1, "author_flair_text": "", "pro_tier": 0, "is_stickied": false, "is_nsfw": false, "is_deleted": false, "is_image": false, "comments": 39, "score_up": 449, "is_edited": false, "is_moderator": false, "awards": 0, "vote_state": 2, "link_metadata": {"twitter": {"quotedTweet": false, "images": false, "linkEmbed": false, "replies": 41, "created": 1768870230000, "id": "2013413792890180093", "video": {"preview": "https://pbs.twimg.com/ext_tw_video_thumb/2013413466929782784/pu/img/ngymg75Pg_3PWhts.jpg", "mpeg": "https://video.twimg.com/ext_tw_video/2013413466929782784/pu/pl/UlKOs8NHm_vmSVEF.m3u8?v=e32", "aspectRatio": [9, 16], "heightRatio": 177, "type": "video/mp4", "url": "https://video.twimg.com/ext_tw_video/2013413466929782784/pu/vid/avc1/320x568/j5nC28vzZQdsfcjt.mp4"}, "poll": false, "user": {"profilePicture": "https://pbs.twimg.com/profile_images/1703913074879590400/clm3F7fX_normal.jpg", "displayName": "The Real Guardrail Guy", "username": "theguardrailguy"}, "content": "Worst Guardrail in America @TVAnews", "parentTweet": false, "likes": 2663}}, "post_flair_text": "", "archive_id": ""}, {"is_locked": false, "tweet_id": "", "sticky_comment": 0, "is_video_mp4": false, "type": "link", "uuid": "1ARws2Lg7W", "is_twitter": false, "is_admin": false, "score": 53, "suggested_sort": 0, "post_flair_class": "hat", "id": 8380912, "raw_content": "", "author": "Trump_Is_My_Daddy", "created": 1769740444842, "profile_picture": "bQrMcb1UUHos", "community": "TheDonald", "ad_tier": 2, "last_comment_author": "FatigueIsReal", "is_video": false, "video_link": "", "is_new_user": false, "domain": "media.scored.co", "is_crosspost": false, "preview": "https://media.scored.co/preview/1ARws2Lg7W.png", "removal_source": "", "link": "https://media.scored.co/post/SQSONzNT2a0E.jpeg", "author_flair_class": "", "is_removed": false, "media": {"resized_resolutions": [{"reference": "/scale/M0dqhPk18yEUvPNz.jpeg", "width": 720, "content-type": "jpeg", "height": 618}], "blurhash": "U48|;a~q00xaIAaeSLM_8_WBkWMxD%xuX7Mx", "full_resolution": [618, 720]}, "title": "Anyone telling you that Stephen Miller\u2019s status in the White House has diminished is obviously an ignorant tool", "last_comment_created": 1769748480598, "content": "", "score_down": 2, "author_flair_text": "", "pro_tier": 0, "is_stickied": false, "is_nsfw": false, "is_deleted": false, "is_image": true, "comments": 20, "score_up": 55, "is_edited": false, "is_moderator": false, "awards": 0, "vote_state": 2, "link_metadata": {"status": 200}, "post_flair_text": "SAVE AMERICA", "archive_id": ""}, {"is_locked": false, "tweet_id": "", "sticky_comment": 0, "is_video_mp4": false, "type": "link", "uuid": "1ARws2KZzX", "is_twitter": false, "is_admin": false, "score": 92, "suggested_sort": 0, "post_flair_class": "", "id": 8380523, "raw_content": "", "author": "TaxDollarsHardAtWork", "created": 1769729621621, "profile_picture": "", "community": "TheDonald", "ad_tier": 2, "last_comment_author": "CommieCrats", "is_video": false, "video_link": "", "is_new_user": false, "domain": "babylonbee.com", "is_crosspost": false, "preview": "https://media.scored.co/preview/1ARws2KZzX.png", "removal_source": "", "link": "https://babylonbee.com/news/bruce-springsteen-threatens-to-keep-releasing-songs-until-deportations-stop", "author_flair_class": "", "is_removed": false, "media": {"resized_resolutions": [], "blurhash": "", "full_resolution": []}, "title": "Bruce Springsteen Threatens To Keep Releasing Songs Until Deportations Stop - Babylon Bee", "last_comment_created": 1769746354279, "content": "", "score_down": 0, "author_flair_text": "", "pro_tier": 0, "is_stickied": false, "is_nsfw": false, "is_deleted": false, "is_image": false, "comments": 4, "score_up": 92, "is_edited": false, "is_moderator": false, "awards": 0, "vote_state": 2, "link_metadata": {"description": "COLTS NECK, NJ \u2014 After putting out a new song titled \"Streets of Minneapolis\" as a show of support for anti-ICE protesters, musician Bruce Springsteen issued a statement threatening to keep releasing songs until deportations were stopped.", "large_image": "yaC5EeYVQrrkaYYH.png", "title": "Bruce Springsteen Threatens To Keep Releasing Songs Until Deportations Stop"}, "post_flair_text": "", "archive_id": ""}, {"is_locked": false, "tweet_id": "", "sticky_comment": 0, "is_video_mp4": false, "type": "link", "uuid": "1ARws3RsW1", "is_twitter": false, "is_admin": false, "score": 38, "suggested_sort": 0, "post_flair_class": "", "id": 8381151, "raw_content": "", "author": "I-am-Orlando", "created": 1769747349283, "profile_picture": "TEnkk5XkT6JN", "community": "TheDonald", "ad_tier": 2, "last_comment_author": "Boomstikchik", "is_video": false, "video_link": "", "is_new_user": false, "domain": "media.scored.co", "is_crosspost": false, "preview": "https://media.scored.co/preview/1ARws3RsW1.png", "removal_source": "", "link": "https://media.scored.co/post/pgePHUneNi3B.jpeg", "author_flair_class": "", "is_removed": false, "media": {"resized_resolutions": [{"reference": "/scale/IhrP0xzRDRx7Wbgu.jpeg", "width": 681, "content-type": "jpeg", "height": 768}], "blurhash": "U37nRS%M9E_3~qIUIU-;xvD%IT-;_3IUIU-;", "full_resolution": [1218, 1080]}, "title": "It\u2019s crazy how close we are to saving the Republic.\n", "last_comment_created": 1769749047637, "content": "", "score_down": 0, "author_flair_text": "", "pro_tier": 1, "is_stickied": false, "is_nsfw": false, "is_deleted": false, "is_image": true, "comments": 7, "score_up": 38, "is_edited": false, "is_moderator": false, "awards": 0, "vote_state": 2, "link_metadata": {"status": 200}, "post_flair_text": "", "archive_id": ""}, {"is_locked": false, "tweet_id": "2016855386087629271", "sticky_comment": 0, "is_video_mp4": false, "type": "link", "uuid": "1ARws2JU80", "is_twitter": true, "is_admin": false, "score": 148, "suggested_sort": 0, "post_flair_class": "", "id": 8380170, "raw_content": "", "author": "blue5707", "created": 1769720137983, "profile_picture": "", "community": "TheDonald", "ad_tier": 2, "last_comment_author": "someguy7738", "is_video": false, "video_link": "", "is_new_user": false, "domain": "twitter.com", "is_crosspost": false, "preview": "https://media.scored.co/preview/1ARws2JU80.png", "removal_source": "", "link": "https://twitter.com/vileTexan/status/2016855386087629271?s=20", "author_flair_class": "", "is_removed": false, "media": {"resized_resolutions": [], "blurhash": "", "full_resolution": []}, "title": "These Trump accounts are a great idea.\n\nWhy don't we do this with Social Security?\n\nPut MY money into MY account that I can see and that the Government doesn't have access to.", "last_comment_created": 1769725318515, "content": "", "score_down": 0, "author_flair_text": "", "pro_tier": 0, "is_stickied": false, "is_nsfw": false, "is_deleted": false, "is_image": false, "comments": 4, "score_up": 148, "is_edited": false, "is_moderator": false, "awards": 0, "vote_state": 2, "link_metadata": {"twitter": {"quotedTweet": false, "images": false, "linkEmbed": false, "replies": 339, "created": 1769690770000, "id": "2016855386087629271", "video": false, "poll": false, "user": {"profilePicture": "https://pbs.twimg.com/profile_images/2006746237672783872/geMLQy8e_normal.jpg", "displayName": "\u272a Evil Te\ud835\udd4fan \u272a", "username": "vileTexan"}, "content": "These Trump accounts are a great idea.\n\nWhy don't we do this with Social Security?\n\nPut MY money into MY account that I can see and that the Government doesn't have access to.", "parentTweet": false, "likes": 5236}}, "post_flair_text": "", "archive_id": ""}, {"is_locked": false, "tweet_id": "", "sticky_comment": 0, "is_video_mp4": false, "type": "link", "uuid": "1ARws2KJPV", "is_twitter": false, "is_admin": false, "score": 93, "suggested_sort": 0, "post_flair_class": "", "id": 8380499, "raw_content": "", "author": "Trick", "created": 1769729029091, "profile_picture": "", "community": "TheDonald", "ad_tier": 2, "last_comment_author": "HanginChad", "is_video": false, "video_link": "", "is_new_user": false, "domain": "www.thegatewaypundit.com", "is_crosspost": false, "preview": "https://media.scored.co/preview/1ARws2KJPV.png", "removal_source": "", "link": "https://www.thegatewaypundit.com/2026/01/another-florida-nurses-license-revoked/", "author_flair_class": "", "is_removed": false, "media": {"resized_resolutions": [], "blurhash": "", "full_resolution": []}, "title": "Florida Revokes Nursing License For Nurse Who Said He Won\u2019t Perform Anesthesia For \u201cMAGA\u201d", "last_comment_created": 1769734302312, "content": "", "score_down": 0, "author_flair_text": "", "pro_tier": 0, "is_stickied": false, "is_nsfw": false, "is_deleted": false, "is_image": false, "comments": 4, "score_up": 93, "is_edited": false, "is_moderator": false, "awards": 0, "vote_state": 2, "link_metadata": {"description": "\u00a0 \u00a0 \u00a0 \u00a0 \u00a0\u00a0Another far-left, hate-filled nurse has lost their Florida nursing license.", "large_image": "UU8akrJDgO8kQ5ib.png", "title": "Florida Revokes Nursing License For Nurse Who Said He Won't Perform Anesthesia For \"MAGA\" | The Gateway Pundit | by Cristina Laila"}, "post_flair_text": "", "archive_id": ""}, {"is_locked": false, "tweet_id": "", "sticky_comment": 0, "is_video_mp4": false, "type": "link", "uuid": "1ARws2LP8d", "is_twitter": false, "is_admin": false, "score": 60, "suggested_sort": 0, "post_flair_class": "", "id": 8380823, "raw_content": "", "author": "Colorado-Living", "created": 1769737589461, "profile_picture": "", "community": "TheDonald", "ad_tier": 2, "last_comment_author": "CommieCrats", "is_video": false, "video_link": "", "is_new_user": false, "domain": "media.scored.co", "is_crosspost": false, "preview": "https://media.scored.co/preview/1ARws2LP8d.png", "removal_source": "", "link": "https://media.scored.co/post/astpLQ1RIbUT.jpeg", "author_flair_class": "", "is_removed": false, "media": {"resized_resolutions": [{"reference": "/scale/KdP38FGAoWjCKS4D.jpeg", "width": 640, "content-type": "jpeg", "height": 427}], "blurhash": "UJMaw=E1~Vot^ANGO7oJ?G-qV{D*O*%LRRV]", "full_resolution": [427, 640]}, "title": "I just got back from the future and this is what I saw", "last_comment_created": 1769746585987, "content": "", "score_down": 0, "author_flair_text": "", "pro_tier": 0, "is_stickied": false, "is_nsfw": false, "is_deleted": false, "is_image": true, "comments": 4, "score_up": 60, "is_edited": false, "is_moderator": false, "awards": 0, "vote_state": 2, "link_metadata": {"status": 200}, "post_flair_text": "", "archive_id": ""}, {"is_locked": false, "tweet_id": "", "sticky_comment": 0, "is_video_mp4": false, "type": "link", "uuid": "1ARws3RbfQ", "is_twitter": false, "is_admin": false, "score": 41, "suggested_sort": 0, "post_flair_class": "fired", "id": 8381084, "raw_content": "", "author": "I-am-Orlando", "created": 1769745439751, "profile_picture": "TEnkk5XkT6JN", "community": "TheDonald", "ad_tier": 2, "last_comment_author": "Abovethefray", "is_video": false, "video_link": "", "is_new_user": false, "domain": "media.scored.co", "is_crosspost": false, "preview": "https://media.scored.co/preview/1ARws3RbfQ.png", "removal_source": "", "link": "https://media.scored.co/post/XeKb9KfsNyDB.jpeg", "author_flair_class": "", "is_removed": false, "media": {"resized_resolutions": [{"reference": "/scale/LU0Zt7hk7vv6MS3w.jpeg", "width": 768, "content-type": "jpeg", "height": 430}], "blurhash": "U#ODIF?wRjMws:NGayoLNas:ayWqoej]ayWV", "full_resolution": [466, 832]}, "title": "This Teacher was fired from her job for posting ICE AGENTS plates on the ANTI ICE map.\n\nTurns out the vehicle was just a random American.\n\nToday she is unemployed.", "last_comment_created": 1769748281157, "content": "", "score_down": 0, "author_flair_text": "", "pro_tier": 1, "is_stickied": false, "is_nsfw": false, "is_deleted": false, "is_image": true, "comments": 9, "score_up": 41, "is_edited": false, "is_moderator": false, "awards": 0, "vote_state": 2, "link_metadata": {"status": 200}, "post_flair_text": "YOU'RE\u00a0\u00a0FIRED!", "archive_id": ""}, {"is_locked": false, "tweet_id": "2016708895859675538", "sticky_comment": 0, "is_video_mp4": false, "type": "link", "uuid": "1ARws2JUGK", "is_twitter": true, "is_admin": false, "score": 140, "suggested_sort": 0, "post_flair_class": "", "id": 8380194, "raw_content": "", "author": "blue5707", "created": 1769720709994, "profile_picture": "", "community": "TheDonald", "ad_tier": 2, "last_comment_author": "MatterThatMetals", "is_video": false, "video_link": "", "is_new_user": false, "domain": "twitter.com", "is_crosspost": false, "preview": "https://media.scored.co/preview/1ARws2JUGK.png", "removal_source": "", "link": "https://twitter.com/TheSCIF/status/2016708895859675538?s=20", "author_flair_class": "", "is_removed": false, "media": {"resized_resolutions": [], "blurhash": "", "full_resolution": []}, "title": "\"I was the hunted, and now I'm the hunter.\"\n\n- President Donald J. Trump", "last_comment_created": 1769723339666, "content": "", "score_down": 1, "author_flair_text": "", "pro_tier": 0, "is_stickied": false, "is_nsfw": false, "is_deleted": false, "is_image": false, "comments": 9, "score_up": 141, "is_edited": false, "is_moderator": false, "awards": 0, "vote_state": 2, "link_metadata": {"twitter": {"quotedTweet": false, "images": false, "linkEmbed": false, "replies": 220, "created": 1769655844000, "id": "2016708895859675538", "video": {"preview": "https://pbs.twimg.com/amplify_video_thumb/2016708620222943233/img/CYOTe2-2lNYRuwdC.jpg", "mpeg": "https://video.twimg.com/amplify_video/2016708620222943233/pl/OvBVi35ahKrAIIRv.m3u8?v=4a6", "aspectRatio": [1, 1], "heightRatio": 100, "type": "video/mp4", "url": "https://video.twimg.com/amplify_video/2016708620222943233/vid/avc1/320x320/7-lOUL6jtVfH7CaA.mp4"}, "poll": false, "user": {"profilePicture": "https://pbs.twimg.com/profile_images/1855406030613585920/mQeRh1p1_normal.jpg", "displayName": "The SCIF", "username": "TheSCIF"}, "content": "They tried to jail him, they stole an election from him, and then they tried to kill him... Now, it's his turn.\n\n\"I was the hunted, and now I'm the hunter.\"\n\n- President Donald J. Trump", "parentTweet": false, "likes": 12154}}, "post_flair_text": "", "archive_id": ""}, {"is_locked": false, "tweet_id": "", "sticky_comment": 0, "is_video_mp4": false, "type": "link", "uuid": "1ARws2Kr2f", "is_twitter": false, "is_admin": false, "score": 79, "suggested_sort": 0, "post_flair_class": "", "id": 8380629, "raw_content": "", "author": "Trick", "created": 1769731890409, "profile_picture": "", "community": "TheDonald", "ad_tier": 2, "last_comment_author": "TGNX", "is_video": false, "video_link": "", "is_new_user": false, "domain": "twitchy.com", "is_crosspost": false, "preview": "https://media.scored.co/preview/1ARws2Kr2f.png", "removal_source": "", "link": "https://twitchy.com/grateful-calvin/2026/01/29/fake-fake-fake-ilhan-omar-loses-it-when-asked-why-she-didnt-follow-foreign-substance-protocol-n2424489", "author_flair_class": "", "is_removed": false, "media": {"resized_resolutions": [], "blurhash": "", "full_resolution": []}, "title": "FAKE, FAKE, FAKE! Ilhan Omar LOSES It When Asked Why She Didn't Follow Foreign Substance Protocols", "last_comment_created": 1769739837360, "content": "", "score_down": 0, "author_flair_text": "", "pro_tier": 0, "is_stickied": false, "is_nsfw": false, "is_deleted": false, "is_image": false, "comments": 6, "score_up": 79, "is_edited": false, "is_moderator": false, "awards": 0, "vote_state": 2, "link_metadata": {"description": "Ilhan Omar reacts dramatically to questions about a foreign substance incident.", "large_image": "xsFlMZZ3N3VsLpki.png", "title": "FAKE, FAKE, FAKE! Ilhan Omar LOSES It When Asked Why She Didn't Follow Foreign Substance Protocols"}, "post_flair_text": "", "archive_id": ""}, {"is_locked": false, "tweet_id": "2017025153360597357", "sticky_comment": 0, "is_video_mp4": false, "type": "link", "uuid": "1ARws2LPbY", "is_twitter": true, "is_admin": false, "score": 51, "suggested_sort": 0, "post_flair_class": "", "id": 8380894, "raw_content": "", "author": "PiratePatriotParrot", "created": 1769740080503, "profile_picture": "", "community": "TheDonald", "ad_tier": 2, "last_comment_author": "CleanUpPhillyTrump24", "is_video": false, "video_link": "", "is_new_user": false, "domain": "twitter.com", "is_crosspost": false, "preview": "https://media.scored.co/preview/1ARws2LPbY.png", "removal_source": "", "link": "https://twitter.com/RedWave_Press/status/2017025153360597357?s=20", "author_flair_class": "", "is_removed": false, "media": {"resized_resolutions": [], "blurhash": "", "full_resolution": []}, "title": "INFURIATING: A savage thug who brutally beat a random stranger nearly to DEATH on a Chicago CTA Pink Line train\u2014leaving the victim in a coma, with traumatic brain injury, broken ribs, fractured skull, and months in the hospital\u2014WALKS FREE with ZERO prison time.\n", "last_comment_created": 1769744163370, "content": "", "score_down": 1, "author_flair_text": "", "pro_tier": 0, "is_stickied": false, "is_nsfw": false, "is_deleted": false, "is_image": false, "comments": 4, "score_up": 52, "is_edited": false, "is_moderator": false, "awards": 0, "vote_state": 2, "link_metadata": {"twitter": {"quotedTweet": false, "images": false, "linkEmbed": false, "replies": 15, "created": 1769731245000, "id": "2017025153360597357", "video": {"preview": "https://pbs.twimg.com/amplify_video_thumb/2017025085257760769/img/A-kxhEQGxiCR-Vnz.jpg", "mpeg": "https://video.twimg.com/amplify_video/2017025085257760769/pl/TiZtJQihySgry6un.m3u8?v=c68", "aspectRatio": [960, 539], "heightRatio": 56, "type": "video/mp4", "url": "https://video.twimg.com/amplify_video/2017025085257760769/vid/avc1/480x270/pP4h_EHThb7OCJoF.mp4"}, "poll": false, "user": {"profilePicture": "https://pbs.twimg.com/profile_images/1720282766225326080/GEDgK6W__normal.jpg", "displayName": "RedWave Press", "username": "RedWave_Press"}, "content": "INFURIATING: A savage thug who brutally beat a random stranger nearly to DEATH on a Chicago CTA Pink Line train\u2014leaving the victim in a coma, with traumatic brain injury, broken ribs, fractured skull, and months in the hospital\u2014WALKS FREE with ZERO prison time.\n\n45-year-old Jesus", "parentTweet": false, "likes": 316}}, "post_flair_text": "", "archive_id": ""}, {"is_locked": false, "tweet_id": "2016972896233816279", "sticky_comment": 0, "is_video_mp4": false, "type": "link", "uuid": "1ARws2LP0T", "is_twitter": true, "is_admin": false, "score": 59, "suggested_sort": 0, "post_flair_class": "takeit", "id": 8380809, "raw_content": "", "author": "PatriotSam", "created": 1769737148997, "profile_picture": "", "community": "TheDonald", "ad_tier": 2, "last_comment_author": "Pretti_The_Terrorist", "is_video": false, "video_link": "", "is_new_user": false, "domain": "twitter.com", "is_crosspost": false, "preview": "https://media.scored.co/preview/1ARws2LP0T.png", "removal_source": "", "link": "https://twitter.com/AFpost/status/2016972896233816279?s=20", "author_flair_class": "", "is_removed": false, "media": {"resized_resolutions": [], "blurhash": "", "full_resolution": []}, "title": "Trump reportedly held covert meetings with Albertian citizens in order to get them to join the United States.", "last_comment_created": 1769739071913, "content": "", "score_down": 1, "author_flair_text": "", "pro_tier": 0, "is_stickied": false, "is_nsfw": false, "is_deleted": false, "is_image": false, "comments": 11, "score_up": 60, "is_edited": false, "is_moderator": false, "awards": 0, "vote_state": 2, "link_metadata": {"twitter": {"quotedTweet": false, "images": [{"width": 682, "heightRatio": 100, "url": "https://pbs.twimg.com/media/G_26KKKbUAAjDyU.jpg", "height": 682}, {"width": 960, "heightRatio": 125, "url": "https://pbs.twimg.com/media/G_26KKIbcAAXPhX.jpg", "height": 1200}], "linkEmbed": false, "replies": 52, "created": 1769718786000, "id": "2016972896233816279", "video": false, "poll": false, "user": {"profilePicture": "https://pbs.twimg.com/profile_images/1623046069109006343/nPSI3ntN_normal.jpg", "displayName": "AF Post", "username": "AFpost"}, "content": "Trump administration officials held covert meetings with Alberta separatists who hope to leave Canada and join the United States.\n\nFollow: @AFpost", "parentTweet": false, "likes": 2109}}, "post_flair_text": "COME AND TAKE IT", "archive_id": ""}, {"is_locked": false, "tweet_id": "", "sticky_comment": 0, "is_video_mp4": false, "type": "link", "uuid": "1ARws2LP4b", "is_twitter": false, "is_admin": false, "score": 58, "suggested_sort": 0, "post_flair_class": "", "id": 8380819, "raw_content": "", "author": "fthecoup", "created": 1769737439355, "profile_picture": "", "community": "TheDonald", "ad_tier": 2, "last_comment_author": "patriotjoe", "is_video": false, "video_link": "", "is_new_user": false, "domain": "www.thegatewaypundit.com", "is_crosspost": false, "preview": "https://media.scored.co/preview/1ARws2LP4b.png", "removal_source": "", "link": "https://www.thegatewaypundit.com/2026/01/president-trump-files-10-billion-lawsuit-against-irs/", "author_flair_class": "", "is_removed": false, "media": {"resized_resolutions": [], "blurhash": "", "full_resolution": []}, "title": "President Trump Files $10 Billion Lawsuit Against IRS for Leaking His Tax Returns", "last_comment_created": 1769742980918, "content": "", "score_down": 2, "author_flair_text": "", "pro_tier": 0, "is_stickied": false, "is_nsfw": false, "is_deleted": false, "is_image": false, "comments": 4, "score_up": 60, "is_edited": false, "is_moderator": false, "awards": 0, "vote_state": 2, "link_metadata": {"description": "\u00a0 \u00a0 \u00a0 \u00a0 \u00a0\u00a0President Trump, Eric Trump, Don Jr., and the Trump Org filed a lawsuit against the IRS for leaking their tax returns.", "large_image": "DQcL5G2t7Ly6Z38K.png", "title": "President Trump Files $10 Billion Lawsuit Against IRS for Leaking His Tax Returns | The Gateway Pundit | by Cristina Laila"}, "post_flair_text": "", "archive_id": ""}, {"is_locked": false, "tweet_id": "2016936345940439527", "sticky_comment": 0, "is_video_mp4": false, "type": "link", "uuid": "1ARws2LPXM", "is_twitter": true, "is_admin": false, "score": 51, "suggested_sort": 0, "post_flair_class": "", "id": 8380880, "raw_content": "", "author": "PiratePatriotParrot", "created": 1769739882078, "profile_picture": "", "community": "TheDonald", "ad_tier": 2, "last_comment_author": "Formerlurker92", "is_video": false, "video_link": "", "is_new_user": false, "domain": "twitter.com", "is_crosspost": false, "preview": "https://media.scored.co/preview/1ARws2LPXM.png", "removal_source": "", "link": "https://twitter.com/RedPillRabbit/status/2016936345940439527?s=20", "author_flair_class": "", "is_removed": false, "media": {"resized_resolutions": [], "blurhash": "", "full_resolution": []}, "title": "NDIAN STUDENTS WITH FAKE CREDENTIALS and papers are getting FULL SCHOLARSHIPS, taking opportunities away from AMERICANS.\n\n\"Aryan Anand, 19, was expelled from the private Pennsylvania university this spring after falsifying documents, including his father\u2019s death certificate, tax documents and an ema", "last_comment_created": 1769744272884, "content": "", "score_down": 1, "author_flair_text": "", "pro_tier": 0, "is_stickied": false, "is_nsfw": false, "is_deleted": false, "is_image": false, "comments": 2, "score_up": 52, "is_edited": false, "is_moderator": false, "awards": 0, "vote_state": 2, "link_metadata": {"twitter": {"quotedTweet": false, "images": [{"width": 1199, "heightRatio": 29, "url": "https://pbs.twimg.com/media/G_2Y6uuWAAA4boS.jpg", "height": 350}], "linkEmbed": false, "replies": 53, "created": 1769710072000, "id": "2016936345940439527", "video": false, "poll": false, "user": {"profilePicture": "https://pbs.twimg.com/profile_images/2011574641786306562/Rq8L1qWc_normal.jpg", "displayName": "Neon White Rabbit", "username": "RedPillRabbit"}, "content": "\ud83d\udea8\ud83d\udea8 INDIAN STUDENTS WITH FAKE CREDENTIALS and papers are getting FULL SCHOLARSHIPS, taking opportunities away from AMERICANS.\n\n\"Aryan Anand, 19, was expelled from the private Pennsylvania university this spring after falsifying documents, including his father\u2019s death", "parentTweet": false, "likes": 2064}}, "post_flair_text": "", "archive_id": ""}, {"is_locked": false, "tweet_id": "", "sticky_comment": 0, "is_video_mp4": false, "type": "link", "uuid": "1ARws2L8Dv", "is_twitter": false, "is_admin": false, "score": 64, "suggested_sort": 0, "post_flair_class": "", "id": 8380747, "raw_content": "", "author": "Zennblack", "created": 1769735318368, "profile_picture": "", "community": "TheDonald", "ad_tier": 2, "last_comment_author": "CommieCrats", "is_video": false, "video_link": "", "is_new_user": false, "domain": "media.scored.co", "is_crosspost": false, "preview": "https://media.scored.co/preview/1ARws2L8Dv.png", "removal_source": "", "link": "https://media.scored.co/post/XBOiOcrZrFWD.jpeg", "author_flair_class": "", "is_removed": false, "media": {"resized_resolutions": [{"reference": "/scale/Ko6ivM2MnH16osIa.png", "width": 216, "content-type": "png", "height": 250}], "blurhash": "UDA,X#M{I;I:?wnht7WXOAIp$%xtI.fiWCs:", "full_resolution": [250, 216]}, "title": "Minnesota right now", "last_comment_created": 1769746626567, "content": "", "score_down": 0, "author_flair_text": "", "pro_tier": 0, "is_stickied": false, "is_nsfw": false, "is_deleted": false, "is_image": true, "comments": 6, "score_up": 64, "is_edited": false, "is_moderator": false, "awards": 0, "vote_state": 2, "link_metadata": {"status": 200}, "post_flair_text": "", "archive_id": ""}, {"is_locked": false, "tweet_id": "2016971272224223363", "sticky_comment": 0, "is_video_mp4": false, "type": "link", "uuid": "1ARws2JTvh", "is_twitter": true, "is_admin": false, "score": 144, "suggested_sort": 0, "post_flair_class": "", "id": 8380145, "raw_content": "", "author": "Mr_Rightside", "created": 1769719446088, "profile_picture": "paLZzzvWVEsN", "community": "TheDonald", "ad_tier": 2, "last_comment_author": "Xinnietheflu3", "is_video": false, "video_link": "", "is_new_user": false, "domain": "twitter.com", "is_crosspost": false, "preview": "https://media.scored.co/preview/1ARws2JTvh.png", "removal_source": "", "link": "https://twitter.com/libsoftiktok/status/2016971272224223363", "author_flair_class": "", "is_removed": false, "media": {"resized_resolutions": [], "blurhash": "", "full_resolution": []}, "title": "BREAKING: Minnesota man Mark Anderson reportedly just tried to break Luigi Mangione out of prison by posing an FBI agent. He came armed with a BBQ fork & pizza cutter. He was promptly arrested & charged with impersonating an agent. There\u2019s something in the water in Minnesota!", "last_comment_created": 1769726353161, "content": "", "score_down": 0, "author_flair_text": "", "pro_tier": 0, "is_stickied": false, "is_nsfw": false, "is_deleted": false, "is_image": false, "comments": 8, "score_up": 144, "is_edited": false, "is_moderator": false, "awards": 0, "vote_state": 2, "link_metadata": {"twitter": {"quotedTweet": false, "images": [{"width": 600, "heightRatio": 133, "url": "https://pbs.twimg.com/media/G_22Q59WIAIQz1P.jpg", "height": 800}, {"width": 1001, "heightRatio": 113, "url": "https://pbs.twimg.com/media/G_22Q6NXEAAQ2eE.jpg", "height": 1134}], "linkEmbed": false, "replies": 121, "created": 1769718399000, "id": "2016971272224223363", "video": false, "poll": false, "user": {"profilePicture": "https://pbs.twimg.com/profile_images/1489097242321428482/sQSUN_M6_normal.jpg", "displayName": "Libs of TikTok", "username": "libsoftiktok"}, "content": "BREAKING: Minnesota man Mark Anderson reportedly just tried to break Luigi Mangione out of prison by posing an FBI agent.\n\nHe came armed with a BBQ fork & pizza cutter.\n\nHe was promptly arrested & charged with impersonating an agent.\n\nThere\u2019s something in the water in Minnesota!", "parentTweet": false, "likes": 780}}, "post_flair_text": "", "archive_id": ""}, {"is_locked": false, "tweet_id": "2016942245379805384", "sticky_comment": 0, "is_video_mp4": false, "type": "link", "uuid": "1ARws2LgaO", "is_twitter": true, "is_admin": false, "score": 44, "suggested_sort": 0, "post_flair_class": "", "id": 8380980, "raw_content": "", "author": "PiratePatriotParrot", "created": 1769742591753, "profile_picture": "", "community": "TheDonald", "ad_tier": 2, "last_comment_author": "HillarysBeaverMunch", "is_video": false, "video_link": "", "is_new_user": false, "domain": "twitter.com", "is_crosspost": false, "preview": "https://media.scored.co/preview/1ARws2LgaO.png", "removal_source": "", "link": "https://twitter.com/lukerosiak/status/2016942245379805384?s=20", "author_flair_class": "", "is_removed": false, "media": {"resized_resolutions": [], "blurhash": "", "full_resolution": []}, "title": "DOD paid $19M to a homeless lady's \"woman-owned business.\" She found a white man to do the work, and kept a cut. When I asked her about it, she ranted about \"evil Jews\" and \"male dominated competitive evil war profiteers.\" \n\nThis is why \n@SecWar\n is cleaning up minority contracting", "last_comment_created": 1769744051726, "content": "", "score_down": 0, "author_flair_text": "", "pro_tier": 0, "is_stickied": false, "is_nsfw": false, "is_deleted": false, "is_image": false, "comments": 3, "score_up": 44, "is_edited": false, "is_moderator": false, "awards": 0, "vote_state": 2, "link_metadata": {"twitter": {"quotedTweet": false, "images": [{"width": 834, "heightRatio": 92, "url": "https://pbs.twimg.com/media/G_2aaUzWgAABBlo.png", "height": 770}], "linkEmbed": false, "replies": 36, "created": 1769711478000, "id": "2016942245379805384", "video": false, "poll": false, "user": {"profilePicture": "https://pbs.twimg.com/profile_images/1468785657573163012/773F_ZRv_normal.jpg", "displayName": "Luke Rosiak", "username": "lukerosiak"}, "content": "DOD paid $19M to a homeless lady's \"woman-owned business.\" She found a white man to do the work, and kept a cut. When I asked her about it, she ranted about \"evil Jews\" and \"male dominated competitive evil war profiteers.\" \n\nThis is why @SecWar is cleaning up minority contracting", "parentTweet": false, "likes": 2083}}, "post_flair_text": "", "archive_id": ""}, {"is_locked": false, "tweet_id": "", "sticky_comment": 0, "is_video_mp4": false, "type": "link", "uuid": "1ARwnVscd6", "is_twitter": false, "is_admin": false, "score": 430, "suggested_sort": 0, "post_flair_class": "nsfcucks", "id": 8379450, "raw_content": "", "author": "Trick", "created": 1769698021481, "profile_picture": "", "community": "TheDonald", "ad_tier": 2, "last_comment_author": "LiteraIIyHitIer", "is_video": false, "video_link": "", "is_new_user": false, "domain": "media.scored.co", "is_crosspost": false, "preview": "https://media.scored.co/preview/1ARwnVscd6.png", "removal_source": "", "link": "https://media.scored.co/post/zuj9ywELKNZx.jpeg", "author_flair_class": "", "is_removed": false, "media": {"resized_resolutions": [{"reference": "/scale/JTrsxYqKrQEhRllk.png", "width": 573, "content-type": "png", "height": 539}], "blurhash": "UjHLe*i_o#M{_NRjt7j[%MozV@ofRjfkWBay", "full_resolution": [539, 573]}, "title": "Coincidence", "last_comment_created": 1769721368990, "content": "", "score_down": 0, "author_flair_text": "", "pro_tier": 0, "is_stickied": false, "is_nsfw": false, "is_deleted": false, "is_image": true, "comments": 6, "score_up": 430, "is_edited": false, "is_moderator": false, "awards": 0, "vote_state": 2, "link_metadata": {"status": 200}, "post_flair_text": "\u00a0\u00a0\u00a0\u00a0\u00a0\u00a0\u00a0\u00a0\u00a0\u00a0\u00a0WEIRD\u00a0\u00a0", "archive_id": ""}, {"is_locked": false, "tweet_id": "", "sticky_comment": 0, "is_video_mp4": false, "type": "link", "uuid": "1ARwnVtAb3", "is_twitter": false, "is_admin": false, "score": 319, "suggested_sort": 0, "post_flair_class": "violent", "id": 8379639, "raw_content": "", "author": "NJTRUMP", "created": 1769703813316, "profile_picture": "", "community": "TheDonald", "ad_tier": 2, "last_comment_author": "MJ_43", "is_video": false, "video_link": "", "is_new_user": false, "domain": "t.me", "is_crosspost": false, "preview": "https://media.scored.co/preview/1ARwnVtAb3.png", "removal_source": "", "link": "https://t.me/SGTnewsNetwork/50676", "author_flair_class": "", "is_removed": false, "media": {"resized_resolutions": [], "blurhash": "", "full_resolution": []}, "title": "Sydney Powell came out and alleged that this was a murder in an attempt to put Kemp into submission.", "last_comment_created": 1769741226011, "content": "", "score_down": 0, "author_flair_text": "", "pro_tier": 0, "is_stickied": false, "is_nsfw": false, "is_deleted": false, "is_image": false, "comments": 9, "score_up": 319, "is_edited": false, "is_moderator": false, "awards": 0, "vote_state": 2, "link_metadata": {"description": "Sydney Powell came out and alleged that this was a murder in an attempt to put Kemp into submission.\u201cWhat we are dealing with here is pervasive and very very dark. Pure evil. They are willing to kill people. Kelly Loeffler\u2019s aid was suddenly blown up in his car on the way to a rally.. He happened to be dating Governor Kemp\u2019s daughter. Governor Kemp was considering an audit at that point\u2026\u201dWhat do you think really happened? Is the timing of this all a coincidence or was there really a plot to stop Trump from proving the election was rigged? Does steel really melt in such a way in car accidents? I\u2019m interested in hearing what your thoughts are.\ud83c\uddfa\ud83c\uddf8Join\ud83d\udc49 @SGTnewsNetwork\ud83d\udcceTwitter\u25aa\ufe0fIG\u25aa\ufe0fTruth Social", "large_image": "BX6vZ3sASGaYr6ab.png", "title": "Sergeant News Network \ud83c\uddfa\ud83c\uddf8"}, "post_flair_text": "\ud83d\udd25\ud83c\udfdb\ufe0f MURDEROUS LEFT \ud83c\udfdb\ufe0f\ud83d\udd25", "archive_id": ""}, {"is_locked": false, "tweet_id": "2017047557633958303", "sticky_comment": 0, "is_video_mp4": false, "type": "link", "uuid": "1ARws3RbfP", "is_twitter": true, "is_admin": false, "score": 39, "suggested_sort": 0, "post_flair_class": "", "id": 8381083, "raw_content": "", "author": "CatalystForChange", "created": 1769745369045, "profile_picture": "", "community": "TheDonald", "ad_tier": 2, "last_comment_author": "HanginChad", "is_video": false, "video_link": "", "is_new_user": false, "domain": "twitter.com", "is_crosspost": false, "preview": "https://media.scored.co/preview/1ARws3RbfP.png", "removal_source": "", "link": "https://twitter.com/NicHulscher/status/2017047557633958303", "author_flair_class": "", "is_removed": false, "media": {"resized_resolutions": [], "blurhash": "", "full_resolution": []}, "title": "Arizona Bill HB 2974 designates modified mRNA injections as biological agents and weapons of mass destruction under state law\u2014classifying their manufacture, possession, or distribution as terrorism, with penalties up to life imprisonment if death occurs. [WHAT? no public hangings?]", "last_comment_created": 1769749582831, "content": "", "score_down": 0, "author_flair_text": "", "pro_tier": 0, "is_stickied": false, "is_nsfw": false, "is_deleted": false, "is_image": false, "comments": 4, "score_up": 39, "is_edited": false, "is_moderator": false, "awards": 0, "vote_state": 2, "link_metadata": {"twitter": {"quotedTweet": {"quotedTweet": false, "images": false, "linkEmbed": false, "replies": 0, "created": 1769723952000, "id": "2016994563898880446", "video": false, "poll": false, "user": {"profilePicture": "https://pbs.twimg.com/profile_images/1586086847423422464/fn0w0p4G_normal.jpg", "displayName": "Dr. Joseph Sansone (JosephSansone.com)", "username": "PhdSansone"}, "content": "BREAKING NEWS: Proposed Arizona Bill Designates MRNA a Bioweapon! State Representative @RJ4arizona  Rachel Jones Keshel Introduced the 'Sansone MRNA Bioweapons Prohibition Act' into Arizona Legislature!\n", "parentTweet": false, "likes": 88}, "images": [{"width": 1101, "heightRatio": 105, "url": "https://pbs.twimg.com/media/G_3-EFrXEAADk1j.jpg", "height": 1159}], "linkEmbed": false, "replies": 39, "created": 1769736587000, "id": "2017047557633958303", "video": false, "poll": false, "user": {"profilePicture": "https://pbs.twimg.com/profile_images/1780360102140112896/tQNtPYCe_normal.jpg", "displayName": "Nicolas Hulscher, MPH", "username": "NicHulscher"}, "content": "\ud83d\udea8BREAKING: Arizona Bill HB 2974 designates modified mRNA injections as biological agents and weapons of mass destruction under state law\u2014classifying their manufacture, possession, or distribution as terrorism, with penalties up to life imprisonment if death occurs.", "parentTweet": false, "likes": 1309}}, "post_flair_text": "", "archive_id": ""}, {"is_locked": false, "tweet_id": "2016987427194208728", "sticky_comment": 0, "is_video_mp4": false, "type": "link", "uuid": "1ARws2KaSR", "is_twitter": true, "is_admin": false, "score": 78, "suggested_sort": 0, "post_flair_class": "", "id": 8380593, "raw_content": "", "author": "PiratePatriotParrot", "created": 1769731255886, "profile_picture": "", "community": "TheDonald", "ad_tier": 2, "last_comment_author": "Thorgasm", "is_video": false, "video_link": "", "is_new_user": false, "domain": "twitter.com", "is_crosspost": false, "preview": "https://media.scored.co/preview/1ARws2KaSR.png", "removal_source": "", "link": "https://twitter.com/DeAngelisCorey/status/2016987427194208728?s=20", "author_flair_class": "", "is_removed": false, "media": {"resized_resolutions": [], "blurhash": "", "full_resolution": []}, "title": "An independent journalist just caught an Associate Dean and Professor at \n@ASU\n admitting they still push DEI.\n\nShe says \"it's kind of embedded.. this is just who we are.\"\n\n \"We started changing language, but we're still doing the same thing.\"\n\n\"It's all still happening.\"", "last_comment_created": 1769737881795, "content": "", "score_down": 0, "author_flair_text": "", "pro_tier": 0, "is_stickied": false, "is_nsfw": false, "is_deleted": false, "is_image": false, "comments": 6, "score_up": 78, "is_edited": false, "is_moderator": false, "awards": 0, "vote_state": 2, "link_metadata": {"twitter": {"quotedTweet": false, "images": false, "linkEmbed": false, "replies": 64, "created": 1769722251000, "id": "2016987427194208728", "video": {"preview": "https://pbs.twimg.com/ext_tw_video_thumb/2016987377000972288/pu/img/tohSCLxM_6secY3P.jpg", "mpeg": "https://video.twimg.com/ext_tw_video/2016987377000972288/pu/pl/5v4shG-Cl6_PMQhj.m3u8?v=12e", "aspectRatio": [16, 9], "heightRatio": 56, "type": "video/mp4", "url": "https://video.twimg.com/ext_tw_video/2016987377000972288/pu/vid/avc1/480x270/h1UrpDMH-0ZlF99o.mp4"}, "poll": false, "user": {"profilePicture": "https://pbs.twimg.com/profile_images/1901301730945773568/fIV_qCwP_normal.jpg", "displayName": "Corey A. DeAngelis, school choice evangelist", "username": "DeAngelisCorey"}, "content": "BREAKING: An independent journalist just caught an Associate Dean and Professor at @ASU admitting they still push DEI.\n\nShe says \"it's kind of embedded.. this is just who we are.\"\n\n \"We started changing language, but we're still doing the same thing.\"\n\n\"It's all still happening.\"", "parentTweet": false, "likes": 2576}}, "post_flair_text": "", "archive_id": ""}], "status": true}